Workbook

Sheet Summary
B1: Summary
B3: General inputs | G3: Options/Warrants | M3: Valuation Summary | O3: 2025 | P3: =O3+1 -> 2026 | Q3: =P3+1 -> 2027
B4: Ticker | C4: HTZ | I4: # | J4: Strike | K4: Dilution | M4: Adj. EV/EBITDA | O4: na | P4: =$C$16/L55 -> 0 | Q4: =$C$16/M55 -> 0
B5: Name | C5: Hertz Global Holdings, Inc. | G5: Warrants (HTZWW) | I5: 82.7 | J5: 13.61 | K5: =MAX(0,I5-((I5*J5)/$C$6)) -> 0
B6: Last price | C6: 4.75 | G6: Exchangeable Notes-2029 | I6: 40.904426 | J6: 6.6252 | K6: =IF($C$6>J6,I6,0) -> 0
B7: Currency | C7: USD | G7: Exchangeable Notes-2030 | I7: 45.995671 | J7: 9.24 | K7: =IF($C$6>J7,I7,0) -> 0
B8: Shares out. all classes (mn) | C8: 312.36068 | G8: RSU/Options | I8: =1.15827+5.471438+26.017278 -> 32.646986 | J8: =(26.17*1.15827+4.04*5.471438+4.96*26.017278)/I8 -> 5.5583151 | K8: =MAX(0,I8-((I8*J8)/$C$6)) -> 0
B9: Net shares outstanding | C9: =K9 -> 312.36068 | G9: Fully diluted shrs | K9: =K8+K5+C8+K6+K7 -> 312.36068
B10: Market capitalization | C10: =C9*C6 -> 1483.7132
B11: Plus: Debt | C11: =E101 -> 5721
B12: Plus: Other | C12: 300 | G12: Main Assets | M12: Main Liabilities
B13: Less: Unrestricted Cash | C13: =SUM(E103:E103) -> -565 | G13: Americas RAC: 442,000 vehicles | M13: ABS: $9.9B
B14: Enterprise Value | C14: =SUM(C10:C13) -> 6939.7132 | G14: International RAC: 96,000 vehicles | M14: Corporate Debt: $5.9B
G15: Brands: Hertz, Dollar, Thrifty. Some franchisees | M15: Airport Locations: 2,000 Americas, 1,500 Intl; leased
G16: 26K employees | M16: Non-Airport Locations: 2,600 Americas, 4,800 Intl; leased
G17: Owned real estate | M17: Self-insured Liabilities
M18: Management team
B19: History
B20: 2005: Ford agreed to sell Hertz to a private-equity consortium led by CD&R, Carlyle, and ML PE, beginning Hertz's modern LBO era.
B21: 2006: IPO in November 2006.
B22: 2011: Acquired Donlen Corporation, expanding into fleet leasing / fleet management beyond pure daily rental cars.
B23: 2012: Acquired Dollar Thrifty Automotive Group; materially strengthened its value-brand exposure through Dollar and Thrifty.
B24: 2014: Hit by a major accounting review / restatement, withdrew guidance, and faced governance turmoil; Carl Icahn built a stake and won board influence, increasing pressure on management and strategy.
B25: 2016: Completed the spin-off of Herc Holdings / Herc Rentals, separating the equipment-rental business and leaving HTZ as a more focused vehicle-rental company
B26: 2020: COVID crushed travel demand; Hertz filed for Chapter 11 in May 2020 as liquidity and used-car-market conditions deteriorated.
B27: 2021: Sold Donlen to Athene during bankruptcy, reducing non-core exposure and raising cash.
B28: 2021: Selected the Certares / Knighthead / Apollo-backed exit proposal
B29: 2021: Relaunched as a public company and made a high-profile EV push, including the widely publicized 100,000 Tesla order and the Uber/Tesla rental partnership.
B30: 2022: Stephen Scherr became CEO; Hertz benefited from the post-COVID travel rebound and posted record full-year 2022 net income and adjusted corporate EBITDA.
... B36: Financial Summary - Consolidated
B37: FY end | E37: 2019 | F37: 2020 | G37: 2021 | H37: =G37+1 -> 2022 | I37: =H37+1 -> 2023 | J37: =I37+1 -> 2024 | K37: =J37+1 -> 2025 | L37: =K37+1 -> 2026 | M37: =L37+1 -> 2027 | N37: =M37+1 -> 2028 | O37: =N37+1 -> 2029 | ... Q37: =P37+1 -> 2031
B38: Revenue | E38: =Financials!T202 -> 9779 | F38: =Financials!Y202 -> 5258 | G38: =Financials!AD202 -> 7337 | H38: =Financials!AI202 -> 8685 | I38: =Financials!AN202 -> 9371 | J38: =Financials!AS202 -> 9049 | K38: =Financials!AX202 -> 8504 | L38: =Financials!BC202 -> 8698.8478 | M38: =Financials!BH202 -> 8872.8248 | N38: =Financials!BI202 -> 9072.5571 | O38: =Financials!BJ202 -> 9228.724 | P38: =Financials!BK202 -> 9413.2985 | Q38: =Financials!BL202 -> 9601.5645
B39: Growth | F39: =F38/E38-1 -> -0.46231721 | G39: =G38/F38-1 -> 0.39539749 | H39: =H38/G38-1 -> 0.18372632 | I39: =I38/H38-1 -> 0.078986759 | J39: =J38/I38-1 -> -0.034361327 | K39: =K38/J38-1 -> -0.060227649 | L39: =L38/K38-1 -> 0.022912493 | M39: =M38/L38-1 -> 0.02 | ... Q39: =Q38/P38-1 -> 0.02
B41: Americas RAC
B42: Average # of Rentable Vehicles | E42: =Financials!T88 -> 534879 | F42: =Financials!Y88 -> 423992.25 | G42: =Financials!AD88 -> 345330.5 | H42: =Financials!AI88 -> 385238 | I42: =Financials!AN88 -> 422485.25 | J42: =Financials!AS88 -> 426410.5 | K42: =Financials!AX88 -> 400355.25 | L42: =Financials!BC88 -> 406377.12 | M42: =Financials!BH88 -> 414504.66 | N42: =Financials!BI88 -> 422794.76 | O42: =Financials!BJ88 -> 431250.65 | P42: =Financials!BK88 -> 439875.67 | Q42: =Financials!BL88 -> 448673.18
B43: Revenue Per Day Growth | E43: =Financials!T106 -> 0.02674146 | F43: =Financials!Y106 -> -0.0066116386 | G43: =Financials!AD106 -> 0.40404419 | H43: =Financials!AI106 -> 0.047442415 | I43: =Financials!AN106 -> -0.052078723 | J43: =Financials!AS106 -> -0.040224576 | K43: =Financials!AX106 -> -0.045237505 | L43: =Financials!BC106 -> 0.010123041 | M43: =Financials!BH106 -> 0 | N43: =Financials!BI106 -> 0 | O43: =Financials!BJ106 -> 0 | P43: =Financials!BK106 -> 0 | Q43: =Financials!BL106 -> 0
B44: Utilization | E44: =Financials!T89 -> 0.79833188 | F44: =Financials!Y89 -> 0.53337314 | G44: =Financials!AD89 -> 0.79341454 | H44: =Financials!AI89 -> 0.79474937 | I44: =Financials!AN89 -> 0.811737 | J44: =Financials!AS89 -> 0.79955292 | K44: =Financials!AX89 -> 0.81746901 | L44: =Financials!BC89 -> 0.82747327 | M44: =Financials!BH89 -> 0.82747327 | N44: =Financials!BI89 -> 0.82747327 | O44: =Financials!BJ89 -> 0.82747327 | P44: =Financials!BK89 -> 0.82747327 | Q44: =Financials!BL89 -> 0.82747327
B45: Direct Operating Expenses per unit per day Growth | E45: =Financials!T110 -> -0.021144301 | F45: =Financials!Y110 -> -0.13275394 | G45: =Financials!AD110 -> 0.42241409 | H45: =Financials!AI110 -> 0.10761521 | I45: =Financials!AN110 -> 0.024029552 | J45: =Financials!AS110 -> 0.019140528 | K45: =Financials!AX110 -> 0.0081127077 | L45: =Financials!BC110 -> -0.049970489 | M45: =Financials!BH110 -> -0.03 | N45: =Financials!BI110 -> -0.03 | O45: =Financials!BJ110 -> -0.03 | P45: =Financials!BK110 -> -0.03 | Q45: =Financials!BL110 -> -0.03
B46: Depreciation per unit per day Growth | E46: =Financials!T109 -> -0.064734058 | F46: =Financials!Y109 -> 0.0043394703 | G46: =Financials!AD109 -> -0.67964007 | H46: =Financials!AI109 -> 0.44102829 | I46: =Financials!AN109 -> 1.9267848 | J46: =Financials!AS109 -> 0.78022765 | K46: =Financials!AX109 -> -0.47434978 | L46: =Financials!BC109 -> -0.10045537 | M46: =Financials!BH109 -> 0 | N46: =Financials!BI109 -> 0 | O46: =Financials!BJ109 -> 0 | P46: =Financials!BK109 -> 0 | Q46: =Financials!BL109 -> 0
B48: International RAC
B49: Average # of Rentable Vehicles | E49: =Financials!T143 -> 180723 | F49: =Financials!Y143 -> 116347.75 | G49: =Financials!AD143 -> 76190.5 | H49: =Financials!AI143 -> 93563.25 | I49: =Financials!AN143 -> 104173.5 | J49: =Financials!AS143 -> 104431.5 | K49: =Financials!AX143 -> 103704.25 | L49: =Financials!BC143 -> 105288.25 | M49: =Financials!BH143 -> 107394.02 | N49: =Financials!BI143 -> 109541.9 | O49: =Financials!BJ143 -> 111732.73 | P49: =Financials!BK143 -> 113967.39 | Q49: =Financials!BL143 -> 116246.74
B50: Revenue Per Day Growth | E50: =Financials!T161 -> 0.00551851 | F50: =Financials!Y161 -> -0.086469045 | G50: =Financials!AD161 -> 0.21784326 | H50: =Financials!AI161 -> 0.16715771 | I50: =Financials!AN161 -> 0.000236888 | J50: =Financials!AS161 -> -0.030116557 | K50: =Financials!AX161 -> 0.0039169334 | L50: =Financials!BC161 -> 0.010117018 | M50: =Financials!BH161 -> 0 | N50: =Financials!BI161 -> 0 | O50: =Financials!BJ161 -> 0 | P50: =Financials!BK161 -> 0 | Q50: =Financials!BL161 -> 0
B51: Utilization | E51: =Financials!T144 -> 0.76009763 | F51: =Financials!Y144 -> 0.5787951 | G51: =Financials!AD144 -> 0.73593652 | H51: =Financials!AI144 -> 0.73446493 | I51: =Financials!AN144 -> 0.7614099 | J51: =Financials!AS144 -> 0.76131722 | K51: =Financials!AX144 -> 0.78710837 | L51: =Financials!BC144 -> 0.79712555 | M51: =Financials!BH144 -> 0.79712555 | N51: =Financials!BI144 -> 0.79712555 | O51: =Financials!BJ144 -> 0.79712555 | P51: =Financials!BK144 -> 0.79712555 | Q51: =Financials!BL144 -> 0.79712555
B52: Direct Operating Expenses per unit per day Growth | E52: =Financials!T165 -> 0.0027987041 | F52: =Financials!Y165 -> -0.12275239 | G52: =Financials!AD165 -> 0.2468435 | H52: =Financials!AI165 -> -0.020123078 | I52: =Financials!AN165 -> 0.085673747 | J52: =Financials!AS165 -> 0.097675767 | K52: =Financials!AX165 -> 0.072167448 | L52: =Financials!BC165 -> -0.04984363 | M52: =Financials!BH165 -> -0.03 | N52: =Financials!BI165 -> 0 | O52: =Financials!BJ165 -> 0 | P52: =Financials!BK165 -> 0 | Q52: =Financials!BL165 -> 0
B53: Depreciation per unit per day Growth | E53: =Financials!T164 -> -0.019612493 | F53: =Financials!Y164 -> -0.031839779 | G53: =Financials!AD164 -> -0.14250141 | H53: =Financials!AI164 -> -0.21740599 | I53: =Financials!AN164 -> 0.60210234 | J53: =Financials!AS164 -> 0.55626533 | K53: =Financials!AX164 -> -0.13692639 | L53: =Financials!BC164 -> -0.068031118 | M53: =Financials!BH164 -> 0 | N53: =Financials!BI164 -> 0 | O53: =Financials!BJ164 -> 0 | P53: =Financials!BK164 -> 0 | Q53: =Financials!BL164 -> 0
B55: Adj. EBITDA | E55: =Financials!T282 -> 657 | F55: =Financials!Y282 -> -1004 | G55: =Financials!AD282 -> 2129 | H55: =Financials!AI282 -> 2305 | I55: =Financials!AN282 -> 561 | J55: =Financials!AS282 -> -1541 | K55: =Financials!AX282 -> -339 | L55: =Financials!BC282 -> 71.170039 | M55: =Financials!BH282 -> 159.88912 | N55: =Financials!BI282 -> 301.72063 | O55: =Financials!BJ282 -> 434.46001 | P55: =Financials!BK282 -> 575.08334 | Q55: =Financials!BL282 -> 717.1677
B56: Margin | E56: =E55/E38 -> 0.067184784 | F56: =F55/F38 -> -0.19094713 | G56: =G55/G38 -> 0.2901731 | H56: =H55/H38 -> 0.26540012 | I56: =I55/I38 -> 0.059865543 | J56: =J55/J38 -> -0.17029506 | K56: =K55/K38 -> -0.039863594 | L56: =L55/L38 -> 0.0081815478 | ... Q56: =Q55/Q38 -> 0.074692796
B57: Growth | F57: =F55/E55-1 -> -2.5281583 | G57: =G55/F55-1 -> -3.1205179 | H57: =H55/G55-1 -> 0.082667919 | I57: =I55/H55-1 -> -0.75661605 | J57: =J55/I55-1 -> -3.7468806 | K57: =K55/J55-1 -> -0.78001298 | L57: =L55/K55-1 -> -1.2099411 | M57: =M55/L55-1 -> 1.2465791 | ... Q57: =Q55/P55-1 -> 0.24706742
B59: Reported FCF | E59: =Financials!T421 -> -42 | F59: =Financials!Y421 -> -734 | G59: =Financials!AD421 -> -869 | H59: =Financials!AI421 -> 1335 | I59: =Financials!AN421 -> -343 | J59: =Financials!AS421 -> -1658 | K59: =Financials!AX421 -> -199 | L59: =Financials!BC421 -> 1562.4023 | M59: =Financials!BH421 -> 1824.8741 | N59: =Financials!BI421 -> 2177.9745 | O59: =Financials!BJ421 -> 2544.3936 | P59: =Financials!BK421 -> 2953.6467 | Q59: =Financials!BL421 -> 3400.015
B60: Margin | E60: =E59/E$38 -> -0.0042949177 | F60: =F59/F$38 -> -0.1395968 | G60: =G59/G$38 -> -0.11844078 | H60: =H59/H$38 -> 0.1537133 | I60: =I59/I$38 -> -0.036602284 | J60: =J59/J$38 -> -0.18322467 | K60: =K59/K$38 -> -0.023400753 | L60: =L59/L$38 -> 0.17961026 | ... Q60: =Q59/Q$38 -> 0.35411053
B62: Total Debt - Vehicle | E62: =Financials!#REF! -> #REF! | F62: =Financials!#REF! -> #REF! | G62: =Financials!#REF! -> #REF! | H62: =Financials!#REF! -> #REF! | I62: =Financials!#REF! -> #REF! | J62: =Financials!#REF! -> #REF! | K62: =Financials!#REF! -> #REF! | L62: =Financials!#REF! -> #REF! | ... Q62: =Financials!#REF! -> #REF!
B63: Total Debt - Non-Vehicle | E63: =Financials!T67 -> 3755 | F63: =Financials!Y67 -> 268 | G63: =Financials!AD67 -> 3055 | H63: =Financials!AI67 -> 3035 | I63: =Financials!AN67 -> 3515 | J63: =Financials!AS67 -> 5170 | K63: =Financials!AX67 -> 5870 | L63: =Financials!BC67 -> 4064.7113 | M63: =Financials!BH67 -> 2263.7553 | N63: =Financials!BI67 -> 111.14329 | O63: =Financials!BJ67 -> -2405.8587 | P63: =Financials!BK67 -> -5329.9226 | Q63: =Financials!BL67 -> -8697.9881
B64: Total Unrestricted Cash | E64: =Financials!T7 -> 865 | F64: =Financials!Y7 -> 1096 | G64: =Financials!AD7 -> 2258 | H64: =Financials!AI7 -> 943 | I64: =Financials!AN7 -> 764 | J64: =Financials!AS7 -> 592 | K64: =Financials!AX7 -> 565 | L64: =Financials!BC7 -> 300 | M64: =Financials!BH7 -> 300 | N64: =Financials!BI7 -> 300 | O64: =Financials!BJ7 -> 300 | P64: =Financials!BK7 -> 300 | Q64: =Financials!BL7 -> 300
B66: Net 1st Lien / Adj. EBITDA | E66: =Financials!T69 -> -0.31202435 | F66: =Financials!Y69 -> 0.84262948 | G66: =Financials!AD69 -> -0.33771724 | H66: =Financials!AI69 -> 0.25292842 | I66: =Financials!AN69 -> 2.2263815 | J66: =Financials!AS69 -> -1.835172 | K66: =Financials!AX69 -> -10.038348 | L66: =Financials!BC69 -> 28.672145 | M66: =Financials!BH69 -> 1.3492074 | N66: =Financials!BI69 -> -6.5035358 | O66: =Financials!BJ69 -> -10.372979 | P66: =Financials!BK69 -> -12.972539 | Q66: =Financials!BL69 -> -15.143329
B67: Net 2nd Lien / Adj. EBITDA | E67: =Financials!T70 -> 0.22070015 | F67: =Financials!Y70 -> 0.84262948 | G67: =Financials!AD70 -> -0.33771724 | H67: =Financials!AI70 -> 0.25292842 | I67: =Financials!AN70 -> 2.2263815 | J67: =Financials!AS70 -> -1.9974043 | K67: =Financials!AX70 -> -10.837758 | L67: =Financials!BC70 -> 32.790643 | M67: =Financials!BH70 -> 3.3320294 | N67: =Financials!BI70 -> -5.3687304 | O67: =Financials!BJ70 -> -9.52184 | P67: =Financials!BK70 -> -12.278086 | Q67: =Financials!BL70 -> -14.54191
B68: Net Total Debt / Adj. EBITDA | E68: =Financials!T71 -> 4.3987823 | F68: =Financials!Y71 -> 0.8247012 | G68: =Financials!AD71 -> 0.37435416 | H68: =Financials!AI71 -> 0.90759219 | I68: =Financials!AN71 -> 4.9037433 | J68: =Financials!AS71 -> -2.9707982 | K68: =Financials!AX71 -> -15.648968 | L68: =Financials!BC71 -> 52.897418 | M68: =Financials!BH71 -> 12.281982 | N68: =Financials!BI71 -> -0.62593237 | O68: =Financials!BJ71 -> -6.2280961 | P68: =Financials!BK71 -> -9.7897507 | Q68: =Financials!BL71 -> -12.546561
B70: Covenants
B71: 1st. Lien Net Leverage (RCF & TL) | L71: 3.5x in 2Q/3Q; 3.0x in 1Q/4Q | M71: 3.5x in 2Q/3Q; 3.0x in 1Q/4Q | N71: 3.5x in 2Q/3Q; 3.0x in 1Q/4Q | O71: 3.5x in 2Q/3Q; 3.0x in 1Q/4Q | P71: 3.5x in 2Q/3Q; 3.0x in 1Q/4Q | Q71: 3.5x in 2Q/3Q; 3.0x in 1Q/4Q
B72: Cushion
B74: Minimum Liquidity | L74: $400M in 2Q/3Q; $500M in 1Q/4Q | M74: $400M in 2Q/3Q; $500M in 1Q/4Q | N74: $400M in 2Q/3Q; $500M in 1Q/4Q | O74: $400M in 2Q/3Q; $500M in 1Q/4Q | P74: $400M in 2Q/3Q; $500M in 1Q/4Q | Q74: $400M in 2Q/3Q; $500M in 1Q/4Q
B75: Cushion
B79: CAPITAL STRUCTURE
D80: Issuer | E80: PF Principal (12/25) | F80: Coupon | G80: Maturity | H80: Fix/Floating | I80: '25 Leverage/LTV | J80: Current Price | K80: Market Value | L80: '25 Leverage/LTV | M80: YTM | N80: Interest Exp | O80: Collateral Package | P80: Guarantors | Q80: Notes
B83: First Lien RCF ($1.665B facility; $543M Available but will have $243M after June 2028) | C83: SOFR+3.00-3.50% | D83: Hertz Corp | E83: =395+346 -> 741 | F83: 0.0828 | G83: 46813 | H83: Floating | J83: 71 | K83: =MIN(E83,J83*E83/100) -> 526.11 | M83: =YIELD(TODAY(),G83,F83,J83, 100,1,1) -> 0.304693 | N83: =F83*E83 -> 61.3548 | O83: 1st lien | P83: HGH, RCIH, US. Subs | Q83: Paid $346M to Well Fargo related to 2021 Bankruptcy in Jan 2026. Owed unsecured bonds make-whole premium and post-petition interest. Minimum liquidity covenant of $400M in 2Q and 3Q and $500M in 1Q and 4Q. $681M LOC. Only $278M of availability by June 2028. Trades in two pieces: REVEXIT and REV EXT. The REVEXIT is maturing June 2026, trading at 96. the REVEXT is the March 2028 maturity one.
B84: Term B Loan | C84: SOFR+3.25-3.50% | D84: Hertz Corp | E84: 1242 | F84: 0.0752 | G84: 46905 | H84: Floating | J84: 72.5 | K84: =MIN(E84,J84*E84/100) -> 900.45 | M84: =YIELD(TODAY(),G84,F84,J84, 100,1,1) -> 0.25592832 | N84: =F84*E84 -> 93.3984 | O84: 1st lien | P84: HGH, RCIH, US. Subs
B85: Incremental Term B Loan | C85: SOFR+3.75% | D85: Hertz Corp | E85: 490 | F85: 0.0766 | G85: 46905 | H85: Floating | J85: 71.5 | K85: =MIN(E85,J85*E85/100) -> 350.35 | M85: =YIELD(TODAY(),G85,F85,J85, 100,1,1) -> 0.26619771 | N85: =F85*E85 -> 37.534 | O85: 1st lien | P85: HGH, RCIH, US. Subs
B86: Term C Loan | C86: SOFR+3.25-3.50% | D86: Hertz Corp | E86: 245 | F86: 0.0752 | G86: 46905 | H86: Floating | J86: 72.5 | K86: =MIN(E86,J86*E86/100) -> 177.625 | M86: =YIELD(TODAY(),G86,F86,J86, 100,1,1) -> 0.25592832 | N86: =F86*E86 -> 18.424 | O86: 1st lien | P86: HGH, RCIH, US. Subs
B87: 12.625% First Lien Senior Secured Notes | D87: Hertz Corp | E87: 1250 | F87: 0.12625 | G87: 47300 | H87: Fixed | J87: 87.5 | K87: =MIN(E87,J87*E87/100) -> 1093.75 | M87: =YIELD(TODAY(),G87,F87,J87, 100,1,1) -> 0.17965494 | N87: =F87*E87 -> 157.8125 | O87: 1st lien | P87: HGH, RCIH, US. Subs
B88: Total 1st Lien Secured Debt | E88: =SUM(E83:E87) -> 3968 | I88: na | K88: =SUM(K83:K87) -> 3048.285 | L88: na | N88: =SUM(N83:N87) -> 368.5237
B90: 8.000% Exchangeable Notes (2L) (PIK) | D90: Hertz Corp | E90: =IF($C$6>$J$6,0,271) -> 271 | F90: 0.08 | G90: 47300 | H90: Fixed | I90: na | J90: 90 | K90: =MIN(E90,J90*E90/100) -> 243.9 | L90: na | M90: =YIELD(TODAY(),G90,F90,J90, 100,1,1) -> 0.11867965 | N90: =F90*E90 -> 21.68 | O90: 2nd lien | P90: HGH, RCIH, US. Subs
B92: 5.500% Exchangeable Sr Notes Due 2030 | D92: Hertz Corp | E92: =IF($C$6>$J$7,0,425) -> 425 | F92: 0.055 | G92: 47757 | H92: Fixed | J92: 55 | K92: =MIN(E92,J92*E92/100) -> 233.75 | M92: =YIELD(TODAY(),G92,F92,J92, 100,1,1) -> 0.22328553 | N92: =F92*E92 -> 23.375 | O92: Unsecured | P92: HGH, RCIH, US. Subs on an unsecured basis
B93: 4.625% Senior Notes Due 2026 | D93: Hertz Corp | E93: 200 | F93: 0.04625 | G93: 46357 | H93: Fixed | J93: 87 | K93: =MIN(E93,J93*E93/100) -> 174 | M93: =YIELD(TODAY(),G93,F93,J93, 100,1,1) -> 0.27629236 | N93: =F93*E93 -> 9.25 | O93: Unsecured | P93: HGH, RCIH, US. Subs on an unsecured basis
B94: 5.000% Senior Notes Due 2029 | D94: Hertz Corp | E94: 1000 | F94: 0.05 | G94: 47453 | H94: Fixed | J94: 40.5 | K94: =MIN(E94,J94*E94/100) -> 405 | M94: =YIELD(TODAY(),G94,F94,J94, 100,1,1) -> 0.37212234 | N94: =F94*E94 -> 50 | O94: Unsecured | P94: HGH, RCIH, US. Subs on an unsecured basis
B95: Other Non-Vehicle Debt | D95: Hertz Corp | E95: 6 | F95: 0.0902 | G95: 60419 | H95: Fixed | J95: na | K95: na | M95: na | N95: =F95*E95 -> 0.5412 | O95: Unsecured | P95: HGH, RCIH, US. Subs on an unsecured basis
B96: Total Unsecured Debt | E96: =SUM(E92:E95) -> 1631 | I96: na | K96: =SUM(K92:K95) -> 812.75 | L96: na | N96: =SUM(N92:N95) -> 83.1662
B98: Total Corporate Debt | E98: =E96+E88+E90 -> 5870 | K98: =K96+K88+K90 -> 4104.935 | N98: =N96+N88+N90 -> 473.3699
B99: Less: Unamortized Debt Issuance Discounts, etc. | E99: =78+54-231-50 -> -149 | G99: Liquidity
G100: Unrestricted Cash | I100: =-E103 -> 565
B101: Total Consolidated Debt (Vehicle & Non-Vehicle) | E101: =E98+E99 -> 5721 | G101: Revolver Availaibility
B102: Plus: Self-Insured Liabilities | E102: =C12 -> 300 | G102: - Total Size (Starting June 2026) | I102: 1665
B103: Less: Unrestricted Cash | E103: =-Financials!AX7 -> -565 | G103: Less: LOC | I103: =-681+200 -> -481
B104: Net Consolidated Debt | E104: =SUM(E101:E103) -> 5456 | G104: Less: Drawn | I104: =-E83 -> -741
B105: Plus: Equity Value | E105: =C10 -> 1483.7132 | G105: Revolver Availaibility | I105: =SUM(I102:I104) -> 443
B106: Enterprise Value | E106: =E105+E104 -> 6939.7132 | G106: Total Current Liquidity | I106: =I105+I100 -> 1008

Sheet Org Chart
B1: Organizational Structure
L3: HERTZ GLOBAL HOLDINGS, INC. (Ultimate Parent, SEC Filer, NASDAQ: HTZ) Cash: $0 at parent level Debt: $0 at parent level No operations. Only an equity/warrant issuer. No Material Assets Parent Guarantor | AJ3: Corporate Credit Facility Guarantor List:
AK5: Hertz Global Holdings, Inc. (Unsecured)
AK6: Rental Car Intermediate Holdings, LLC
AK7: Dollar Rent A Car, Inc.
AK8: Dollar Thrifty Automotive Group, Inc.
AK9: DTG Operations, Inc.
AK10: DTG Supply, LLC
Q11: │ | R11: 100% | AC11: LEGEND ■ Yellow: Financing / Debt ■ Green: Core Operations ■ Black: Holdco / Support | AK11: Firefly Rent A Car LLC
M12: Rental Car Intermediate Holdings, LLC (Intermediate Holdco, Delaware) Pass-through; no independent operations Guarantor | AK12: Hertz Car Sales LLC
AK13: Hertz Global Services Corporation
AK14: Hertz Local Edition Corp.
AK15: Hertz Local Edition Transporting, Inc.
Q16: │ | R16: 100% | AK16: Hertz System, Inc.
J17: THE HERTZ CORPORATION (SEC Co-Filer, Main OpCo & Debt Issuer/Borrower, Delaware) ALL operations, revenue, assets, fleet, & EBITDA sit here and below Non-Vehicle (Corporate) Debt: $5.9B The only corporate debt issuer | AK17: Hertz Technologies, Inc.
AK18: Hertz Transporting, Inc.
AK19: Rental Car Group Company, LLC
AK20: Smartz Vehicle Rental Corporation
AK21: Thrifty Car Sales, Inc.
AK22: Thrifty, LLC
AK23: Thrifty Rent-A-Car System, LLC
AK24: TRAC Asia Pacific, Inc.
AK25: Hertz FHV #1, LLC
AK26: Hertz FHV #2, LLC
AK27: Hertz FHV #3, LLC
C28: ─── | D28: ─── | E28: ─┬─ | F28: ─── | G28: ─── | H28: ─── | I28: ─── | J28: ─── | K28: ─── | L28: ─┬─ | M28: ─── | N28: ─── | O28: ─── | P28: ─── | Q28: ─── | R28: ─┴─ | S28: ─── | T28: ─── | U28: ─── | V28: ─── | W28: ─── | X28: ─┬─ | Y28: ─── | Z28: ─── | AA28: ─── | AB28: ─── | AC28: ─── | AD28: ─┬─ | AE28: ─── | AF28: ─── | AK28: Hertz FHV #4, LLC
E29: │ | F29: 100% | L29: │ | M29: 100% | R29: │ | S29: 100% | X29: │ | Y29: 100% (mostly) | AD29: │ | AE29: 100% | AK29: Hertz FHV #5, LLC
B30: Hertz Vehicle Financing III LLC (HVF III — US Vehicle ABS Issuer) Delaware SPV, Bankruptcy-Remote Vehicle Debt: $9.9B Multiple ABS series (2021-1 thru 2025-6) VFN (variable funding): $1.5B Medium term notes: $8.3B Ring-fenced from corporate creditors | J30: Americas RAC Segment (Core US / Canada / LatAm Operations) Key operating subsidiaries: • Dollar Thrifty Auto Group, Inc. • Firefly Rent A Car LLC • Hertz Car Sales LLC • Hertz FHV #1 through #13, LLC • Thrifty Insurance Agency, Inc. • Hertz Car Exchange, Inc. | Q30: International RAC Segment (Europe, UK, Australia, NZ & Other) Key Operating Subsidiaries: • Hertz (UK) Limited • Hertz Autovermietung GmbH (DE) • Hertz Italiana Srl (IT) | X30: Intl Fleet Financing Entities (European ABS & Other Vehicle Debt) Generally not directly owned by The Hertz Corporation, but sits in regional/international structure. But they are not typically owned by international operating subs Vehicle Debt: $1.8B Intl Fleet Financing No. 2 B.V. (25% owned) Hertz Fleet Financing UK Ltd European ABS Canadian Securitization Austrialian Securitization New Zealand RCF UK ABS Ring-fenced from corporate creditors | AE30: Other Subsidiaries Insurance / Captive: • Probus Insurance Co. Europe Ltd. (Ireland) • Hertz Intl RE Ltd. (IE) Treasury / Finance: • Hertz Intl Treasury Limited (Ireland) • Hertz Finance Centre Limited (Ireland) Legacy / Misc Subs | AK30: Hertz FHV #6, LLC
AK31: Hertz FHV #7, LLC
AK32: Hertz FHV #8, LLC
AK33: Hertz FHV #9, LLC
AK34: Hertz FHV #10, LLC
AK35: Hertz FHV #11, LLC
AK36: Hertz FHV #12, LLC
AK37: Hertz FHV #13, LLC
AK38: Hertz FHV #14, LLC
AK39: Hertz FHV #15, LLC
AK40: Hertz FHV #16, LLC
AK41: Hertz Mobility Holdings, LLC
AJ43: ABS financing subs ring-fenced

Sheet Financials
B1: Financial Statements - HTZ
B3: Balance Sheet
E5: =F5-1 -> 2004 | F5: =G5-1 -> 2005 | G5: =H5-1 -> 2006 | H5: =I5-1 -> 2007 | I5: =J5-1 -> 2008 | J5: =K5-1 -> 2009 | K5: =L5-1 -> 2010 | L5: =M5-1 -> 2011 | ... Q5: =R5-1 -> 2016 | R5: 2017 | S5: =R5+1 -> 2018 | T5: =S5+1 -> 2019 | U5: 1Q | V5: 2Q | W5: 3Q | X5: 4Q | Y5: =T5+1 -> 2020 | Z5: 1Q | AA5: 2Q | AB5: 3Q | AC5: 4Q | AD5: =Y5+1 -> 2021 | AE5: 1Q | AF5: 2Q | AG5: 3Q | AH5: 4Q | AI5: =AD5+1 -> 2022 | AJ5: 1Q | AK5: 2Q | AL5: 3Q | AM5: 4Q | AN5: =AI5+1 -> 2023 | AO5: 1Q | AP5: 2Q | AQ5: 3Q | AR5: 4Q | AS5: =AN5+1 -> 2024 | AT5: 1Q | AU5: 2Q | AV5: 3Q | AW5: 4Q | AX5: =AS5+1 -> 2025 | AY5: 1Q | AZ5: 2Q | BA5: 3Q | BB5: 4Q | BC5: =AX5+1 -> 2026 | BD5: 1Q | BE5: 2Q | BF5: 3Q | BG5: 4Q | BH5: =BC5+1 -> 2027 | BI5: =BH5+1 -> 2028 | BJ5: =BI5+1 -> 2029 | BK5: =BJ5+1 -> 2030 | BL5: =BK5+1 -> 2031
B6: Assets
C7: Cash and cash equivalents | E7: 1072 | F7: 1072 | G7: 1072 | H7: 1072 | I7: 1072 | J7: 1072 | K7: 1072 | L7: 1072 | M7: 1072 | N7: 1072 | O7: 1072 | P7: 1072 | Q7: 1072 | R7: 1072 | S7: 1127 | T7: 865 | U7: 1017 | V7: 1366 | W7: 1137 | X7: 1096 | Y7: =X7 -> 1096 | Z7: 1087 | AA7: 1820 | AB7: 2703 | AC7: 2258 | AD7: =AC7 -> 2258 | AE7: 1521 | AF7: 1041 | AG7: 1006 | AH7: 943 | AI7: =AH7 -> 943 | AJ7: 728 | AK7: 682 | AL7: 594 | AM7: 764 | AN7: =AM7 -> 764 | AO7: 465 | AP7: 568 | AQ7: 501 | AR7: 592 | AS7: =AR7 -> 592 | AT7: 626 | AU7: 503 | AV7: 1095 | AW7: 565 | AX7: =AW7 -> 565 | AY7: =AY419-AY8 -> 300 | AZ7: =AZ419-AZ8 -> 300 | BA7: =BA419-BA8 -> 300 | BB7: =BB419-BB8 -> 300 | BC7: =BB7 -> 300 | BD7: =BD419-BD8 -> 300 | BE7: =BE419-BE8 -> 300 | BF7: =BF419-BF8 -> 300 | BG7: =BG419-BG8 -> 300 | BH7: =BG7 -> 300 | BI7: =BI419-BI8 -> 300 | BJ7: =BJ419-BJ8 -> 300 | BK7: =BK419-BK8 -> 300 | BL7: =BL419-BL8 -> 300
C8: Restricted cash and cash equivalents | E8: 432 | F8: 432 | G8: 432 | H8: 432 | I8: 432 | J8: 432 | K8: 432 | L8: 432 | M8: 432 | N8: 432 | O8: 432 | P8: 432 | Q8: 432 | R8: 432 | S8: 283 | T8: 495 | U8: 392 | V8: 945 | W8: 745 | X8: 411 | Y8: =X8 -> 411 | Z8: 1353 | AA8: 875 | AB8: 763 | AC8: 393 | AD8: =AC8 -> 393 | AE8: 601 | AF8: 522 | AG8: 502 | AH8: 475 | AI8: =AH8 -> 475 | AJ8: 514 | AK8: 484 | AL8: 462 | AM8: 442 | AN8: =AM8 -> 442 | AO8: 480 | AP8: 426 | AQ8: 404 | AR8: 541 | AS8: =AR8 -> 541 | AT8: 395 | AU8: 626 | AV8: 454 | AW8: 602 | AX8: =AW8 -> 602 | AY8: =AW8 -> 602 | AZ8: =AY8 -> 602 | BA8: =AZ8 -> 602 | BB8: =BA8 -> 602 | BC8: =BB8 -> 602 | BD8: =BB8 -> 602 | BE8: =BD8 -> 602 | BF8: =BE8 -> 602 | BG8: =BF8 -> 602 | BH8: =BG8 -> 602 | BI8: =BH8 -> 602 | BJ8: =BI8 -> 602 | BK8: =BJ8 -> 602 | BL8: =BK8 -> 602
C9: Total receivables, net | E9: 1365 | F9: 1365 | G9: 1365 | H9: 1365 | I9: 1365 | J9: 1365 | K9: 1365 | L9: 1365 | M9: 1365 | N9: 1365 | O9: 1365 | P9: 1365 | Q9: 1365 | R9: 1365 | S9: 1587 | T9: 1840 | U9: 2095 | V9: 1566 | W9: 1416 | X9: 777 | Y9: =X9 -> 777 | Z9: 793 | AA9: 1024 | AB9: 890 | AC9: 758 | AD9: =AC9 -> 758 | AE9: 800 | AF9: 975 | AG9: 1053 | AH9: 974 | AI9: =AH9 -> 974 | AJ9: 1034 | AK9: 1292 | AL9: 1407 | AM9: 1191 | AN9: =AM9 -> 1191 | AO9: 1213 | AP9: 1267 | AQ9: 1340 | AR9: 1205 | AS9: =AR9 -> 1205 | AT9: 1232 | AU9: 1150 | AV9: 1210 | AW9: 1110 | AX9: =AW9 -> 1110 | AY9: =AY56*AY54 -> 1117.4099 | AZ9: =AZ56*AZ54 -> 1122.4732 | BA9: =BA56*BA54 -> 1128.7159 | BB9: =BB56*BB54 -> 1135.4329 | BC9: =BB9 -> 1135.4329 | BD9: =BD56*BD54 -> 1140.314 | BE9: =BE56*BE54 -> 1146.1193 | BF9: =BF56*BF54 -> 1152.713 | BG9: =BG56*BG54 -> 1158.1415 | BH9: =BG9 -> 1158.1415 | BI9: =BI56*BI54 -> 1184.2119 | BJ9: =BJ56*BJ54 -> 1204.5959 | BK9: =BK56*BK54 -> 1228.6878 | BL9: =BL56*BL54 -> 1253.2616
C10: Prepaid expenses and other assets | E10: 687 | F10: 687 | G10: 687 | H10: 687 | I10: 687 | J10: 687 | K10: 687 | L10: 687 | M10: 687 | N10: 687 | O10: 687 | P10: 687 | Q10: 687 | R10: 687 | S10: 902 | T10: 689 | U10: 1121 | V10: 563 | W10: 429 | X10: 373 | Y10: =X10 -> 373 | Z10: 786 | AA10: 1184 | AB10: 642 | AC10: 1017 | AD10: =AC10 -> 1017 | AE10: 1331 | AF10: 1094 | AG10: 934 | AH10: 1155 | AI10: =AH10 -> 1155 | AJ10: 980 | AK10: 1031 | AL10: 835 | AM10: 726 | AN10: =AM10 -> 726 | AO10: 751 | AP10: 754 | AQ10: 927 | AR10: 894 | AS10: =AR10 -> 894 | AT10: 1010 | AU10: 739 | AV10: 780 | AW10: 782 | AX10: =AW10 -> 782 | AY10: =AY54*AY57 -> 787.22031 | AZ10: =AZ54*AZ57 -> 790.78746 | BA10: =BA54*BA57 -> 795.18546 | BB10: =BB54*BB57 -> 799.91757 | BC10: =BB10 -> 799.91757 | BD10: =BD54*BD57 -> 803.35633 | BE10: =BE54*BE57 -> 807.44618 | BF10: =BF54*BF57 -> 812.09151 | BG10: =BG54*BG57 -> 815.91592 | BH10: =BG10 -> 815.91592 | BI10: =BI54*BI57 -> 834.28265 | BJ10: =BJ54*BJ57 -> 848.64325 | BK10: =BK54*BK57 -> 865.61611 | BL10: =BL54*BL57 -> 882.92844
C11: Other current assets | E11: 0 | F11: 0 | G11: 0 | H11: 0 | I11: 0 | J11: 0 | K11: 0 | L11: 0 | M11: 0 | N11: 0 | O11: 0 | P11: 0 | Q11: 0 | R11: 0 | S11: 0 | T11: 0 | U11: 0 | V11: 0 | W11: 0 | X11: 0 | Y11: =X11 -> 0 | Z11: 0 | AA11: 0 | AB11: 0 | AC11: 0 | AD11: =AC11 -> 0 | AE11: 0 | AF11: 0 | AG11: 0 | AH11: 0 | AI11: =AH11 -> 0 | AJ11: 0 | AK11: 0 | AL11: 0 | AM11: 0 | AN11: =AM11 -> 0 | AO11: 0 | AP11: 0 | AQ11: 0 | AR11: 0 | AS11: =AR11 -> 0 | AT11: 0 | AU11: 0 | AV11: 0 | AW11: 0 | AX11: =AW11 -> 0 | AY11: =AX11 -> 0 | AZ11: =AY11 -> 0 | BA11: =AZ11 -> 0 | BB11: =BA11 -> 0 | BC11: =BB11 -> 0 | BD11: =BC11 -> 0 | BE11: =BD11 -> 0 | ... BL11: =BK11 -> 0
C12: Total current assets | E12: =SUM(E7:E11) -> 3556 | F12: =SUM(F7:F11) -> 3556 | G12: =SUM(G7:G11) -> 3556 | H12: =SUM(H7:H11) -> 3556 | I12: =SUM(I7:I11) -> 3556 | J12: =SUM(J7:J11) -> 3556 | K12: =SUM(K7:K11) -> 3556 | L12: =SUM(L7:L11) -> 3556 | ... BL12: =SUM(BL7:BL11) -> 3038.19
C14: Revenue earning vehicles:
C15: Vehicles | E15: 14574 | F15: 14574 | G15: 14574 | H15: 14574 | I15: 14574 | J15: 14574 | K15: 14574 | L15: 14574 | M15: 14574 | N15: 14574 | O15: 14574 | P15: 14574 | Q15: 14574 | R15: 14574 | S15: 15703 | T15: 17085 | U15: 17646 | V15: 15340 | W15: 11462 | X15: 7540 | Y15: =X15 -> 7540 | Z15: 7919 | AA15: 9563 | AB15: 10122 | AC15: 10836 | AD15: =AC15 -> 10836 | AE15: 12118 | AF15: 13962 | AG15: 13757 | AH15: 14281 | AI15: =AH15 -> 14281 | AJ15: 15746 | AK15: 17833 | AL15: 17576 | AM15: 16806 | AN15: =AM15 -> 16806 | AO15: 17052 | AP15: 18122 | AQ15: 13543 | AR15: 12714 | AS15: =AR15 -> 12714 | AT15: 13139 | AU15: 14468 | AV15: 14023 | AW15: 14039 | AX15: =AW15 -> 14039
C16: Less: accumulated depreciation | E16: -3238 | F16: -3238 | G16: -3238 | H16: -3238 | I16: -3238 | J16: -3238 | K16: -3238 | L16: -3238 | M16: -3238 | N16: -3238 | O16: -3238 | P16: -3238 | Q16: -3238 | R16: -3238 | S16: -3284 | T16: -3296 | U16: -3337 | V16: -3275 | W16: -3011 | X16: -1478 | Y16: =X16 -> -1478 | Z16: -1559 | AA16: -1573 | AB16: -1559 | AC16: -1610 | AD16: =AC16 -> -1610 | AE16: -1554 | AF16: -1632 | AG16: -1734 | AH16: -1786 | AI16: =AH16 -> -1786 | AJ16: -1888 | AK16: -1988 | AL16: -2117 | AM16: -2155 | AN16: =AM16 -> -2155 | AO16: -2435 | AP16: -2753 | AQ16: -308 | AR16: -751 | AS16: =AR16 -> -751 | AT16: -986 | AU16: -1173 | AV16: -1330 | AW16: -1513 | AX16: =AW16 -> -1513
C17: Total revenue earning vehicles, net | E17: =E16+E15 -> 11336 | F17: =F16+F15 -> 11336 | G17: =G16+G15 -> 11336 | H17: =H16+H15 -> 11336 | I17: =I16+I15 -> 11336 | J17: =J16+J15 -> 11336 | K17: =K16+K15 -> 11336 | L17: =L16+L15 -> 11336 | ... X17: =X16+X15 -> 6062 | Y17: =X17 -> 6062 | Z17: =Z16+Z15 -> 6360 | AA17: =AA16+AA15 -> 7990 | AB17: =AB16+AB15 -> 8563 | AC17: =AC16+AC15 -> 9226 | AD17: =AC17 -> 9226 | AE17: =AE16+AE15 -> 10564 | AF17: =AF16+AF15 -> 12330 | AG17: =AG16+AG15 -> 12023 | AH17: =AH16+AH15 -> 12495 | AI17: =AH17 -> 12495 | AJ17: =AJ16+AJ15 -> 13858 | AK17: =AK16+AK15 -> 15845 | AL17: =AL16+AL15 -> 15459 | AM17: =AM16+AM15 -> 14651 | AN17: =AM17 -> 14651 | AO17: =AO16+AO15 -> 14617 | AP17: =AP16+AP15 -> 15369 | AQ17: =AQ16+AQ15 -> 13235 | AR17: =AR16+AR15 -> 11963 | AS17: =AR17 -> 11963 | AT17: =AT16+AT15 -> 12153 | AU17: =AU16+AU15 -> 13295 | AV17: =AV16+AV15 -> 12693 | AW17: =AW16+AW15 -> 12526 | AX17: =AW17 -> 12526 | AY17: =AX17-Y385-AY356 -> 12176.974 | AZ17: =AY17-Z385-AZ356 -> 11773.894 | BA17: =AZ17-AA385-BA356 -> 11325.954 | BB17: =BA17-AB385-BB356 -> 10893.81 | BC17: =BB17 -> 10893.81 | BD17: =BC17-AD385-BD356 -> 10508.843 | BE17: =BD17-AE385-BE356 -> 10118.522 | BF17: =BE17-AF385-BF356 -> 9682.4631 | BG17: =BF17-AG385-BG356 -> 9262.1962 | BH17: =BG17 -> 9262.1962 | BI17: =BH17-AI385-BI356 -> 7569.4501 | BJ17: =BI17-AJ385-BJ356 -> 5734.8491 | BK17: =BJ17-AK385-BK356 -> 3895.6561 | BL17: =BK17-AL385-BL356 -> 1968.1192
C18: Property and equipment, net | E18: 840 | F18: 840 | G18: 840 | H18: 840 | I18: 840 | J18: 840 | K18: 840 | L18: 840 | M18: 840 | N18: 840 | O18: 840 | P18: 840 | Q18: 840 | R18: 840 | S18: 778 | T18: 757 | U18: 765 | V18: 724 | W18: 699 | X18: 666 | Y18: =X18 -> 666 | Z18: 637 | AA18: 618 | AB18: 609 | AC18: 608 | AD18: =AC18 -> 608 | AE18: 611 | AF18: 605 | AG18: 618 | AH18: 637 | AI18: =AH18 -> 637 | AJ18: 642 | AK18: 665 | AL18: 672 | AM18: 671 | AN18: =AM18 -> 671 | AO18: 667 | AP18: 670 | AQ18: 639 | AR18: 623 | AS18: =AR18 -> 623 | AT18: 595 | AU18: 586 | AV18: 570 | AW18: 566 | AX18: =AW18 -> 566 | AY18: =AX18-AY385-AY357 -> 561 | AZ18: =AY18-AZ385-AZ357 -> 557 | BA18: =AZ18-BA385-BA357 -> 553 | BB18: =BA18-BB385-BB357 -> 549 | BC18: =BB18 -> 549 | BD18: =BC18-BD385-BD357 -> 544 | BE18: =BD18-BE385-BE357 -> 540 | BF18: =BE18-BF385-BF357 -> 536 | BG18: =BF18-BG385-BG357 -> 532 | BH18: =BG18 -> 532 | BI18: =BH18-BI385-BI357 -> 515 | BJ18: =BI18-BJ385-BJ357 -> 498 | BK18: =BJ18-BK385-BK357 -> 481 | BL18: =BK18-BL385-BL357 -> 464
C19: Operating lease right-of-use assets | E19: 0 | F19: 0 | G19: 0 | H19: 0 | I19: 0 | J19: 0 | K19: 0 | L19: 0 | M19: 0 | N19: 0 | O19: 0 | P19: 0 | Q19: 0 | R19: 0 | S19: 0 | T19: 1871 | U19: 1832 | V19: 1719 | W19: 1737 | X19: 1675 | Y19: =X19 -> 1675 | Z19: 1580 | AA19: 1504 | AB19: 1453 | AC19: 1566 | AD19: =AC19 -> 1566 | AE19: 1566 | AF19: 1562 | AG19: 1632 | AH19: 1887 | AI19: =AH19 -> 1887 | AJ19: 2067 | AK19: 2169 | AL19: 2200 | AM19: 2253 | AN19: =AM19 -> 2253 | AO19: 2211 | AP19: 2229 | AQ19: 2033 | AR19: 2088 | AS19: =AR19 -> 2088 | AT19: 2140 | AU19: 2286 | AV19: 2288 | AW19: 2257 | AX19: =AW19 -> 2257 | AY19: =AX19 -> 2257 | AZ19: =AY19 -> 2257 | BA19: =AZ19 -> 2257 | BB19: =BA19 -> 2257 | BC19: =BB19 -> 2257 | BD19: =BC19 -> 2257 | BE19: =BD19 -> 2257 | ... BL19: =BK19 -> 2257
C20: Intangible assets, net | E20: 3242 | F20: 3242 | G20: 3242 | H20: 3242 | I20: 3242 | J20: 3242 | K20: 3242 | L20: 3242 | M20: 3242 | N20: 3242 | O20: 3242 | P20: 3242 | Q20: 3242 | R20: 3242 | S20: 3203 | T20: 3238 | U20: 3231 | V20: 3088 | W20: 3062 | X20: 2992 | Y20: =X20 -> 2992 | Z20: 2969 | AA20: 2947 | AB20: 2925 | AC20: 2912 | AD20: =AC20 -> 2912 | AE20: 2903 | AF20: 2893 | AG20: 2883 | AH20: 2887 | AI20: =AH20 -> 2887 | AJ20: 2882 | AK20: 2883 | AL20: 2881 | AM20: 2863 | AN20: =AM20 -> 2863 | AO20: 2862 | AP20: 2858 | AQ20: 2856 | AR20: 2852 | AS20: =AR20 -> 2852 | AT20: 2852 | AU20: 2853 | AV20: 2855 | AW20: 2858 | AX20: =AW20 -> 2858 | AY20: =AX20 -> 2858 | AZ20: =AY20 -> 2858 | BA20: =AZ20 -> 2858 | BB20: =BA20 -> 2858 | BC20: =BB20 -> 2858 | BD20: =BC20 -> 2858 | BE20: =BD20 -> 2858 | ... BL20: =BK20 -> 2858
C21: Goodwill | E21: 1084 | F21: 1084 | G21: 1084 | H21: 1084 | I21: 1084 | J21: 1084 | K21: 1084 | L21: 1084 | M21: 1084 | N21: 1084 | O21: 1084 | P21: 1084 | Q21: 1084 | R21: 1084 | S21: 1083 | T21: 1083 | U21: 1080 | V21: 1080 | W21: 1081 | X21: 1045 | Y21: =X21 -> 1045 | Z21: 1045 | AA21: 1045 | AB21: 1045 | AC21: 1045 | AD21: =AC21 -> 1045 | AE21: 1044 | AF21: 1044 | AG21: 1043 | AH21: 1044 | AI21: =AH21 -> 1044 | AJ21: 1044 | AK21: 1044 | AL21: 1044 | AM21: 1044 | AN21: =AM21 -> 1044 | AO21: 1044 | AP21: 1044 | AQ21: 1044 | AR21: 1044 | AS21: =AR21 -> 1044 | AT21: 1044 | AU21: 1045 | AV21: 1045 | AW21: 1045 | AX21: =AW21 -> 1045 | AY21: =AX21 -> 1045 | AZ21: =AY21 -> 1045 | BA21: =AZ21 -> 1045 | BB21: =BA21 -> 1045 | BC21: =BB21 -> 1045 | BD21: =BC21 -> 1045 | BE21: =BD21 -> 1045 | ... BL21: =BK21 -> 1045
C22: Assets held for sale | X22: 1811 | Y22: =X22 -> 1811 | Z22: 0 | AA22: 0
C23: Total assets | E23: =SUM(E17:E22)+E12 -> 20058 | F23: =SUM(F17:F22)+F12 -> 20058 | G23: =SUM(G17:G22)+G12 -> 20058 | H23: =SUM(H17:H22)+H12 -> 20058 | I23: =SUM(I17:I22)+I12 -> 20058 | J23: =SUM(J17:J22)+J12 -> 20058 | K23: =SUM(K17:K22)+K12 -> 20058 | L23: =SUM(L17:L22)+L12 -> 20058 | ... BL23: =SUM(BL17:BL22)+BL12 -> 11630.309
B25: Liabilities
C26: Accounts payable | E26: 946 | F26: 946 | G26: 946 | H26: 946 | I26: 946 | J26: 946 | K26: 946 | L26: 946 | M26: 946 | N26: 946 | O26: 946 | P26: 946 | Q26: 946 | R26: 946 | S26: 988 | T26: 943 | U26: 998 | V26: 516 | W26: 585 | X26: 418 | Y26: =X26 -> 418 | Z26: 531 | AA26: 780 | AB26: 586 | AC26: 572 | AD26: =AC26 -> 572 | AE26: 675 | AF26: 659 | AG26: 614 | AH26: 657 | AI26: =AH26 -> 657 | AJ26: 720 | AK26: 935 | AL26: 790 | AM26: 701 | AN26: =AM26 -> 701 | AO26: 1134 | AP26: 995 | AQ26: 624 | AR26: 642 | AS26: =AR26 -> 642 | AT26: 861 | AU26: 898 | AV26: 830 | AW26: 859 | AX26: =AW26 -> 859 | AY26: =AY54*AY58 -> 864.73433 | AZ26: =AZ54*AZ58 -> 868.65272 | BA26: =BA54*BA58 -> 873.48377 | BB26: =BB54*BB58 -> 878.68183 | BC26: =BB26 -> 878.68183 | BD26: =BD54*BD58 -> 882.45919 | BE26: =BE54*BE58 -> 886.95175 | BF26: =BF54*BF58 -> 892.05449 | BG26: =BG54*BG58 -> 896.25547 | BH26: =BG26 -> 896.25547 | BI26: =BI54*BI58 -> 916.43068 | BJ26: =BJ54*BJ58 -> 932.20531 | BK26: =BK54*BK58 -> 950.84942 | BL26: =BL54*BL58 -> 969.8664
C27: Accrued liabilities | E27: 920 | F27: 920 | G27: 920 | H27: 920 | I27: 920 | J27: 920 | K27: 920 | L27: 920 | M27: 920 | N27: 920 | O27: 920 | P27: 920 | Q27: 920 | R27: 920 | S27: 1304 | T27: 1032 | U27: 982 | V27: 836 | W27: 810 | X27: 759 | Y27: =X27 -> 759 | Z27: 824 | AA27: 945 | AB27: 904 | AC27: 863 | AD27: =AC27 -> 863 | AE27: 939 | AF27: 1048 | AG27: 955 | AH27: 911 | AI27: =AH27 -> 911 | AJ27: 926 | AK27: 971 | AL27: 896 | AM27: 860 | AN27: =AM27 -> 860 | AO27: 883 | AP27: 931 | AQ27: 1176 | AR27: 1174 | AS27: =AR27 -> 1174 | AT27: 1191 | AU27: 1336 | AV27: 1257 | AW27: 1231 | AX27: =AW27 -> 1231 | AY27: =AY54*AY59 -> 1239.2176 | AZ27: =AZ54*AZ59 -> 1244.8329 | BA27: =BA54*BA59 -> 1251.7561 | BB27: =BB54*BB59 -> 1259.2053 | BC27: =BB27 -> 1259.2053 | BD27: =BD54*BD59 -> 1264.6185 | BE27: =BE54*BE59 -> 1271.0566 | BF27: =BF54*BF59 -> 1278.3691 | BG27: =BG54*BG59 -> 1284.3894 | BH27: =BG27 -> 1284.3894 | BI27: =BI54*BI59 -> 1313.3017 | BJ27: =BJ54*BJ59 -> 1335.9077 | BK27: =BK54*BK59 -> 1362.6259 | BL27: =BL54*BL59 -> 1389.8784
C28: Accrued taxes, net | E28: 160 | F28: 160 | G28: 160 | H28: 160 | I28: 160 | J28: 160 | K28: 160 | L28: 160 | M28: 160 | N28: 160 | O28: 160 | P28: 160 | Q28: 160 | R28: 160 | S28: 136 | T28: 150 | U28: 133 | V28: 97 | W28: 119 | X28: 121 | Y28: =X28 -> 121 | Z28: 161 | AA28: 232 | AB28: 228 | AC28: 157 | AD28: =AC28 -> 157 | AE28: 188 | AF28: 206 | AG28: 205 | AH28: 170 | AI28: =AH28 -> 170 | AJ28: 173 | AK28: 229 | AL28: 215 | AM28: 157 | AN28: =AM28 -> 157 | AO28: 177 | AP28: 208 | AQ28: 222 | AR28: 158 | AS28: =AR28 -> 158 | AT28: 198 | AU28: 168 | AV28: 127 | AW28: 131 | AX28: =AW28 -> 131 | AY28: =AW28 -> 131 | AZ28: =AY28 -> 131 | BA28: =AZ28 -> 131 | BB28: =BA28 -> 131 | BC28: =BB28 -> 131 | BD28: =BB28 -> 131 | BE28: =BD28 -> 131 | BF28: =BE28 -> 131 | BG28: =BF28 -> 131 | BH28: =BG28 -> 131 | BI28: =BH28 -> 131 | BJ28: =BI28 -> 131 | BK28: =BJ28 -> 131 | BL28: =BK28 -> 131
C29: Debt - Vehicle | E29: 10431 | F29: 10431 | G29: 10431 | H29: 10431 | I29: 10431 | J29: 10431 | K29: 10431 | L29: 10431 | M29: 10431 | N29: 10431 | O29: 10431 | P29: 10431 | Q29: 10431 | R29: 10431 | S29: 11902 | T29: 13368 | U29: 14438 | V29: 12924 | W29: 8753 | X29: 6024 | Y29: =X29 -> 6024 | Z29: 6286 | AA29: 7035 | AB29: 7207 | AC29: 7921 | AD29: =AC29 -> 7921 | AE29: 9098 | AF29: 10411 | AG29: 10097 | AH29: 10886 | AI29: =AH29 -> 10886 | AJ29: 11789 | AK29: 13100 | AL29: 12894 | AM29: 12242 | AN29: =AM29 -> 12242 | AO29: 11846 | AP29: 12774 | AQ29: 12303 | AR29: =16335-AR30 -> 11231 | AS29: =AR29 -> 11231 | AT29: =16772-AT30 -> 11026 | AU29: 12202 | AV29: 11759 | AW29: 11629 | AX29: =AW29 -> 11629 | AY29: =AX29+AY395+AY396 -> 11629 | AZ29: =AY29+AZ395+AZ396 -> 11629 | BA29: =AZ29+BA395+BA396 -> 11629 | BB29: =BA29+BB395+BB396 -> 11629 | BC29: =BB29 -> 11629 | BD29: =BC29+BD395+BD396 -> 11629 | BE29: =BD29+BE395+BE396 -> 11629 | BF29: =BE29+BF395+BF396 -> 11629 | BG29: =BF29+BG395+BG396 -> 11629 | BH29: =BG29 -> 11629 | BI29: =BH29+BI395+BI396 -> 11629 | BJ29: =BI29+BJ395+BJ396 -> 11629 | BK29: =BJ29+BK395+BK396 -> 11629 | BL29: =BK29+BL395+BL396 -> 11629
C30: Debt - Non-Vehicle | E30: 4434 | F30: 4434 | G30: 4434 | H30: 4434 | I30: 4434 | J30: 4434 | K30: 4434 | L30: 4434 | M30: 4434 | N30: 4434 | O30: 4434 | P30: 4434 | Q30: 4434 | R30: 4434 | S30: 4422 | T30: 3721 | U30: 4316 | V30: 58 | W30: 18 | X30: 243 | Y30: =X30 -> 243 | Z30: 740 | AA30: 1514 | AB30: 1511 | AC30: 2986 | AD30: =AC30 -> 2986 | AE30: 2984 | AF30: 2981 | AG30: 2979 | AH30: 2977 | AI30: =AH30 -> 2977 | AJ30: 2975 | AK30: 3470 | AL30: 3119 | AM30: 3449 | AN30: =AM30 -> 3449 | AO30: 3898 | AP30: 4595 | AQ30: 4653 | AR30: 5104 | AS30: =AR30 -> 5104 | AT30: 5746 | AU30: 5434 | AV30: 5649 | AW30: =5425+346 -> 5771 | AX30: =AW30 -> 5771 | AY30: =AY302-AY303 -> 5317.6638 | AZ30: =AZ302-AZ303 -> 4906.7307 | BA30: =BA302-BA303 -> 4267.5051 | BB30: =BB302-BB303 -> 3965.7113 | BC30: =BB30 -> 3965.7113 | BD30: =BD302-BD303 -> 3718.0675 | BE30: =BE302-BE303 -> 3242.0751 | BF30: =BF302-BF303 -> 2532.0692 | BG30: =BG302-BG303 -> 2164.7553 | BH30: =BG30 -> 2164.7553 | BI30: =BI302-BI303 -> 12.143292 | BJ30: =BJ302-BJ303 -> -2504.8587 | BK30: =BK302-BK303 -> -5428.9226 | BL30: =BL302-BL303 -> -8796.9881
C31: Public Warrants | Y31: =X31 -> 0 | AA31: 800 | AB31: 783 | AC31: 1324 | AD31: =AC31 -> 1324 | AE31: 1272 | AF31: 811 | AG31: 737 | AH31: 617 | AI31: =AH31 -> 617 | AJ31: 735 | AK31: 835 | AL31: 506 | AM31: 453 | AN31: =AM31 -> 453 | AO31: 367 | AP31: 203 | AQ31: 181 | AR31: 178 | AS31: =AR31 -> 178 | AT31: 187 | AU31: 302 | AV31: 308 | AW31: 222 | AX31: =AW31 -> 222 | AY31: =AW31 -> 222 | AZ31: =AY31 -> 222 | BA31: =AZ31 -> 222 | BB31: =BA31 -> 222 | BC31: =BB31 -> 222 | BD31: =BB31 -> 222 | BE31: =BD31 -> 222 | BF31: =BE31 -> 222 | BG31: =BF31 -> 222 | BH31: =BG31 -> 222 | BI31: =BH31 -> 222 | BJ31: =BI31 -> 222 | BK31: =BJ31 -> 222 | BL31: =BK31 -> 222
C32: Operating lease liabilities | E32: 0 | F32: 0 | G32: 0 | H32: 0 | I32: 0 | J32: 0 | K32: 0 | L32: 0 | M32: 0 | N32: 0 | O32: 0 | P32: 0 | Q32: 0 | R32: 0 | T32: 1848 | U32: 1844 | V32: 1690 | W32: 1703 | X32: 1636 | Y32: =X32 -> 1636 | Z32: 1541 | AA32: 1459 | AB32: 1402 | AC32: 1510 | AD32: =AC32 -> 1510 | AE32: 1502 | AF32: 1493 | AG32: 1556 | AH32: 1802 | AI32: =AH32 -> 1802 | AJ32: 1977 | AK32: 2072 | AL32: 2094 | AM32: 2142 | AN32: =AM32 -> 2142 | AO32: 2100 | AP32: 2108 | AQ32: 2021 | AR32: 2073 | AS32: =AR32 -> 2073 | AT32: 2125 | AU32: 2280 | AV32: 2292 | AW32: 2275 | AX32: =AW32 -> 2275 | AY32: =AW32 -> 2275 | AZ32: =AY32 -> 2275 | BA32: =AZ32 -> 2275 | BB32: =BA32 -> 2275 | BC32: =BB32 -> 2275 | BD32: =BB32 -> 2275 | BE32: =BD32 -> 2275 | BF32: =BE32 -> 2275 | BG32: =BF32 -> 2275 | BH32: =BG32 -> 2275 | BI32: =BH32 -> 2275 | BJ32: =BI32 -> 2275 | BK32: =BJ32 -> 2275 | BL32: =BK32 -> 2275
C33: Self-insured liabilities | E33: 427 | F33: 427 | G33: 427 | H33: 427 | I33: 427 | J33: 427 | K33: 427 | L33: 427 | M33: 427 | N33: 427 | O33: 427 | P33: 427 | Q33: 427 | R33: 427 | S33: 418 | T33: 553 | U33: 532 | V33: 495 | W33: 481 | X33: 488 | Y33: =X33 -> 488 | Z33: 470 | AA33: 459 | AB33: 470 | AC33: 463 | AD33: =AC33 -> 463 | AE33: 468 | AF33: 470 | AG33: 484 | AH33: 472 | AI33: =AH33 -> 472 | AJ33: 457 | AK33: 451 | AL33: 472 | AM33: 471 | AN33: =AM33 -> 471 | AO33: 473 | AP33: 501 | AQ33: 559 | AR33: 617 | AS33: =AR33 -> 617 | AT33: 627 | AU33: 640 | AV33: 660 | AW33: 648 | AX33: =AW33 -> 648 | AY33: =AW33 -> 648 | AZ33: =AY33 -> 648 | BA33: =AZ33 -> 648 | BB33: =BA33 -> 648 | BC33: =BB33 -> 648 | BD33: =BB33 -> 648 | BE33: =BD33 -> 648 | BF33: =BE33 -> 648 | BG33: =BF33 -> 648 | BH33: =BG33 -> 648 | BI33: =BH33 -> 648 | BJ33: =BI33 -> 648 | BK33: =BJ33 -> 648 | BL33: =BK33 -> 648
C34: Deferred income taxes, net | E34: 1220 | F34: 1220 | G34: 1220 | H34: 1220 | I34: 1220 | J34: 1220 | K34: 1220 | L34: 1220 | M34: 1220 | N34: 1220 | O34: 1220 | P34: 1220 | Q34: 1220 | R34: 1220 | S34: 1092 | T34: 1124 | U34: 1108 | V34: 915 | W34: 887 | X34: 730 | Y34: =X34 -> 730 | Z34: 789 | AA34: 711 | AB34: 851 | AC34: 1010 | AD34: =AC34 -> 1010 | AE34: 1113 | AF34: 1258 | AG34: 1306 | AH34: 1360 | AI34: =AH34 -> 1360 | AJ34: 1223 | AK34: 1193 | AL34: 1178 | AM34: 1038 | AN34: =AM34 -> 1038 | AO34: 620 | AP34: 912 | AQ34: 559 | AR34: 472 | AS34: =AR34 -> 472 | AT34: 348 | AU34: 327 | AV34: 425 | AW34: 350 | AX34: =AW34 -> 350 | AY34: =AW34 -> 350 | AZ34: =AY34 -> 350 | BA34: =AZ34 -> 350 | BB34: =BA34 -> 350 | BC34: =BB34 -> 350 | BD34: =BB34 -> 350 | BE34: =BD34 -> 350 | BF34: =BE34 -> 350 | BG34: =BF34 -> 350 | BH34: =BG34 -> 350 | BI34: =BH34 -> 350 | BJ34: =BI34 -> 350 | BK34: =BJ34 -> 350 | BL34: =BK34 -> 350
C35: Liabilities subject to compromise | V35: 4912 | W35: 5001 | X35: 4965 | Y35: =X35 -> 4965 | Z35: 4978 | AA35: 0
C36: Liabilities held for sale | V36: 0 | X36: 1431 | Y36: =X36 -> 1431 | Z36: 0 | AA36: 0
C37: Total liabilities | E37: =SUM(E26:E36) -> 18538 | F37: =SUM(F26:F36) -> 18538 | G37: =SUM(G26:G36) -> 18538 | H37: =SUM(H26:H36) -> 18538 | I37: =SUM(I26:I36) -> 18538 | J37: =SUM(J26:J36) -> 18538 | K37: =SUM(K26:K36) -> 18538 | L37: =SUM(L26:L36) -> 18538 | ... BL37: =SUM(BL26:BL36) -> 8817.7567
B39: Equity
C40: Preferred stock | E40: 0 | F40: 0 | G40: 0 | H40: 0 | I40: 0 | J40: 0 | K40: 0 | L40: 0 | M40: 0 | N40: 0 | O40: 0 | P40: 0 | Q40: 0 | R40: 0 | S40: 0 | T40: 0 | U40: 0 | V40: 0 | W40: 0 | X40: 0 | Y40: =X40 -> 0 | Z40: 0 | AA40: 1433 | AB40: 1433 | AC40: 0 | AD40: =AC40 -> 0 | AE40: 0 | AF40: 0 | AG40: 0 | AH40: 0 | AI40: =AH40 -> 0 | AJ40: 0 | AK40: 0 | AL40: 0 | AM40: 0 | AN40: =AM40 -> 0 | AO40: 0 | AP40: 0 | AQ40: 0 | AR40: 0 | AS40: =AR40 -> 0 | AT40: 0 | AU40: 0 | AV40: 0 | AW40: 0 | AX40: =AW40 -> 0 | AY40: =AX40 -> 0 | AZ40: =AY40 -> 0 | BA40: =AZ40 -> 0 | BB40: =BA40 -> 0 | BC40: =BB40 -> 0 | BD40: =BC40 -> 0 | BE40: =BD40 -> 0 | ... BL40: =BK40 -> 0
C41: Common stock | E41: 1 | F41: 1 | G41: 1 | H41: 1 | I41: 1 | J41: 1 | K41: 1 | L41: 1 | M41: 1 | N41: 1 | O41: 1 | P41: 1 | Q41: 1 | R41: 1 | S41: 1 | T41: 1 | U41: 1 | V41: 2 | W41: 2 | X41: 2 | Y41: =X41 -> 2 | Z41: 2 | AA41: 5 | AB41: 5 | AC41: 5 | AD41: =AC41 -> 5 | AE41: 5 | AF41: 5 | AG41: 5 | AH41: 5 | AI41: =AH41 -> 5 | AJ41: 5 | AK41: 5 | AL41: 5 | AM41: 5 | AN41: =AM41 -> 5 | AO41: 5 | AP41: 5 | AQ41: 5 | AR41: 5 | AS41: =AR41 -> 5 | AT41: 5 | AU41: 5 | AV41: 5 | AW41: 5 | AX41: =AW41 -> 5 | AY41: =AX41 -> 5 | AZ41: =AY41 -> 5 | BA41: =AZ41 -> 5 | BB41: =BA41 -> 5 | BC41: =BB41 -> 5 | BD41: =BC41 -> 5 | BE41: =BD41 -> 5 | ... BL41: =BK41 -> 5
C42: Treasury stock | E42: -100 | F42: -100 | G42: -100 | H42: -100 | I42: -100 | J42: -100 | K42: -100 | L42: -100 | M42: -100 | N42: -100 | O42: -100 | P42: -100 | Q42: -100 | R42: -100 | S42: -100 | T42: -100 | U42: -100 | V42: -100 | W42: -100 | X42: -100 | Y42: =X42 -> -100 | Z42: -100 | AA42: 0 | AB42: 0 | AC42: -708 | AD42: =AC42 -> -708 | AE42: -1430 | AF42: -2321 | AG42: -2821 | AH42: -3136 | AI42: =AH42 -> -3136 | AJ42: -3237 | AK42: -3338 | AL42: -3389 | AM42: -3430 | AN42: =AM42 -> -3430 | AO42: -3430 | AP42: -3430 | AQ42: -3430 | AR42: -3430 | AS42: =AR42 -> -3430 | AT42: -3430 | AU42: -3430 | AV42: -3430 | AW42: -3430 | AX42: =AW42 -> -3430 | AY42: =AX42 -> -3430 | AZ42: =AY42 -> -3430 | BA42: =AZ42 -> -3430 | BB42: =BA42 -> -3430 | BC42: =BB42 -> -3430 | BD42: =BC42 -> -3430 | BE42: =BD42 -> -3430 | ... BL42: =BK42 -> -3430
C43: Additional paid-in capital | E43: 2243 | F43: 2243 | G43: 2243 | H43: 2243 | I43: 2243 | J43: 2243 | K43: 2243 | L43: 2243 | M43: 2243 | N43: 2243 | O43: 2243 | P43: 2243 | Q43: 2243 | R43: 2243 | S43: 2261 | T43: 3024 | U43: 3022 | V43: 3048 | W43: 3047 | X43: 3047 | Y43: =X43 -> 3047 | Z43: 3049 | AA43: 6476 | AB43: 6482 | AC43: 6209 | AD43: =AC43 -> 6209 | AE43: 6237 | AF43: 6274 | AG43: 6308 | AH43: 6326 | AI43: =AH43 -> 6326 | AJ43: 6346 | AK43: 6369 | AL43: 6389 | AM43: 6405 | AN43: =AM43 -> 6405 | AO43: 6351 | AP43: 6365 | AQ43: 6380 | AR43: 6396 | AS43: =AR43 -> 6396 | AT43: 6409 | AU43: 6421 | AV43: 6432 | AW43: 6447 | AX43: =AW43 -> 6447 | AY43: =AX43 -> 6447 | AZ43: =AY43 -> 6447 | BA43: =AZ43 -> 6447 | BB43: =BA43 -> 6447 | BC43: =BB43 -> 6447 | BD43: =BC43 -> 6447 | BE43: =BD43 -> 6447 | ... BL43: =BK43 -> 6447
C44: Retained earnings (Accumulated deficit) | E44: -506 | F44: -506 | G44: -506 | H44: -506 | I44: -506 | J44: -506 | K44: -506 | L44: -506 | M44: -506 | N44: -506 | O44: -506 | P44: -506 | Q44: -506 | R44: -506 | S44: -909 | T44: -967 | U44: -1323 | V44: -2170 | W44: -2392 | X44: -2681 | Y44: =X44 -> -2681 | Z44: -2491 | AA44: -2659 | AB44: -2055 | AC44: -2315 | AD44: =AC44 -> -2315 | AE44: -1889 | AF44: -949 | AG44: -372 | AH44: -256 | AI44: =AH44 -> -256 | AJ44: -60 | AK44: 79 | AL44: 708 | AM44: -248 | AN44: =AM44 -> -248 | AO44: 174 | AP44: -691 | AQ44: -2023 | AR44: -2502 | AS44: =AR44 -> -2502 | AT44: -2945 | AU44: -3239 | AV44: -3055 | AW44: -3249 | AX44: =AW44 -> -3249 | AY44: =AX44+AY266+AY361+AY363 -> -3514.0115 | AZ44: =AY44+AZ266+AZ361+AZ363 -> -3520.0617 | BA44: =AZ44+BA266+BA361+BA363 -> -3341.8896 | BB44: =BA44+BB266+BB361+BB363 -> -3501.438 | BC44: =BB44 -> -3501.438 | BD44: =BC44+BD266+BD361+BD363 -> -3715.6314 | BE44: =BD44+BE266+BE361+BE363 -> -3664.9961 | BF44: =BE44+BF266+BF361+BF363 -> -3425.2252 | BG44: =BF44+BG266+BG361+BG363 -> -3528.1465 | BH44: =BG44 -> -3528.1465 | BI44: =BH44+BI266+BI361+BI363 -> -3239.931 | BJ44: =BI44+BJ266+BJ361+BJ363 -> -2623.166 | BK44: =BJ44+BK266+BK361+BK363 -> -1637.5927 | BL44: =BK44+BL266+BL361+BL363 -> -246.44743
C45: Accumulated other comprehensive income (loss) | E45: -118 | F45: -118 | G45: -118 | H45: -118 | I45: -118 | J45: -118 | K45: -118 | L45: -118 | M45: -118 | N45: -118 | O45: -118 | P45: -118 | Q45: -118 | R45: -118 | S45: -192 | T45: -189 | U45: -228 | V45: -221 | W45: -216 | X45: -212 | Y45: =X45 -> -212 | Z45: -195 | AA45: -202 | AB45: -226 | AC45: -214 | AD45: =AC45 -> -214 | AE45: -221 | AF45: -280 | AG45: -359 | AH45: -294 | AI45: =AH45 -> -294 | AJ45: -280 | AK45: -276 | AL45: -323 | AM45: 360 | AN45: =AM45 -> 360 | AO45: -288 | AP45: -291 | AQ45: -251 | AR45: -316 | AS45: =AR45 -> -316 | AT45: -301 | AU45: -261 | AV45: -269 | AW45: =-232-346 -> -578 | AX45: =AW45 -> -578 | AY45: =AX45 -> -578 | AZ45: =AY45 -> -578 | BA45: =AZ45 -> -578 | BB45: =BA45 -> -578 | BC45: =BB45 -> -578 | BD45: =BC45 -> -578 | BE45: =BD45 -> -578 | ... BL45: =BK45 -> -578
C46: Noncontrolling interests | E46: 0 | F46: 0 | G46: 0 | H46: 0 | I46: 0 | J46: 0 | K46: 0 | L46: 0 | M46: 0 | N46: 0 | O46: 0 | P46: 0 | Q46: 0 | R46: 0 | S46: 59 | T46: 119 | U46: 119 | V46: 114 | W46: 59 | X46: 37 | Y46: =X46 -> 37 | Z46: 25 | AA46: 19 | AB46: 12
C47: Total equity | E47: =SUM(E40:E46) -> 1520 | F47: =SUM(F40:F46) -> 1520 | G47: =SUM(G40:G46) -> 1520 | H47: =SUM(H40:H46) -> 1520 | I47: =SUM(I40:I46) -> 1520 | J47: =SUM(J40:J46) -> 1520 | K47: =SUM(K40:K46) -> 1520 | L47: =SUM(L40:L46) -> 1520 | ... BL47: =SUM(BL40:BL46) -> 2197.5526
C49: Total liabilities and SHE | E49: =E47+E37 -> 20058 | F49: =F47+F37 -> 20058 | G49: =G47+G37 -> 20058 | H49: =H47+H37 -> 20058 | I49: =I47+I37 -> 20058 | J49: =J47+J37 -> 20058 | K49: =K47+K37 -> 20058 | L49: =L47+L37 -> 20058 | ... BL49: =BL47+BL37 -> 11015.309
C51: Balancing line | E51: =ABS(E49-E23) -> 0 | F51: =ABS(F49-F23) -> 0 | G51: =ABS(G49-G23) -> 0 | H51: =ABS(H49-H23) -> 0 | I51: =ABS(I49-I23) -> 0 | J51: =ABS(J49-J23) -> 0 | K51: =ABS(K49-K23) -> 0 | L51: =ABS(L49-L23) -> 0 | ... BL51: =ABS(BL49-BL23) -> 615
AZ52: =AZ51-AY51 -> 9 | BA52: =BA51-AZ51 -> 8 | BB52: =BB51-BA51 -> 24 | BC52: =BC51-BB51 -> 0 | BD52: =BD51-BC51 -> 71 | BE52: =BE51-BD51 -> 30 | BF52: =BF51-BE51 -> 29 | BG52: =BG51-BF51 -> 45 | ... BL52: =BL51-BK51 -> 28
C53: Working Capital
C54: LTM Revenue | E54: =E202 -> 8803 | F54: =F202 -> 8803 | G54: =G202 -> 8803 | H54: =H202 -> 8803 | I54: =I202 -> 8803 | J54: =J202 -> 8803 | K54: =K202 -> 8803 | L54: =L202 -> 8803 | ... T54: =T202 -> 9779 | Y54: =Y202 -> 5258 | Z54: =SUM(Z202,V202:X202) -> 4624 | AA54: =SUM(Z202:AA202,W202:X202) -> 5665 | AB54: =SUM(Z202:AB202,X202) -> 6623 | AC54: =SUM(Z202:AC202) -> 7337 | AD54: =AC54 -> 7337 | AE54: =SUM(AE202,AA202:AC202) -> 7858 | AF54: =SUM(AE202:AF202,AB202:AC202) -> 8329 | AG54: =SUM(AE202:AG202,AC202) -> 8599 | AH54: =SUM(AE202:AH202) -> 8685 | AI54: =AH54 -> 8685 | AJ54: =SUM(AJ202,AF202:AH202) -> 8922 | AK54: =SUM(AJ202:AK202,AG202:AH202) -> 9015 | AL54: =SUM(AJ202:AL202,AH202) -> 9222 | AM54: =SUM(AJ202:AM202) -> 9371 | AN54: =AM54 -> 9371 | AO54: =SUM(AO202,AK202:AM202) -> 9404 | AP54: =SUM(AO202:AP202,AL202:AM202) -> 9320 | AQ54: =SUM(AO202:AQ202,AM202) -> 9193 | AR54: =SUM(AO202:AR202) -> 9049 | AS54: =AR54 -> 9049 | AT54: =SUM(AT202,AP202:AR202) -> 8782 | AU54: =SUM(AT202:AU202,AQ202:AR202) -> 8614 | AV54: =SUM(AT202:AV202,AR202) -> 8516 | AW54: =SUM(AT202:AW202) -> 8504 | AX54: =AW54 -> 8504 | AY54: =SUM(AY202,AU202:AW202) -> 8560.7692 | AZ54: =SUM(AY202:AZ202,AV202:AW202) -> 8599.5608 | BA54: =SUM(AY202:BA202,AW202) -> 8647.3876 | BB54: =SUM(AY202:BB202) -> 8698.8478 | BC54: =BB54 -> 8698.8478 | BD54: =SUM(BD202,AZ202:BB202) -> 8736.2432 | BE54: =SUM(BD202:BE202,BA202:BB202) -> 8780.7191 | BF54: =SUM(BD202:BF202,BB202) -> 8831.2356 | BG54: =SUM(BD202:BG202) -> 8872.8248 | BH54: =BG54 -> 8872.8248 | BI54: =BI202 -> 9072.5571 | BJ54: =BJ202 -> 9228.724 | BK54: =BK202 -> 9413.2985 | BL54: =BL202 -> 9601.5645
C55: Restricted Cash As % of LTM Rev | E55: =E8/E54 -> 0.049074179 | F55: =F8/F54 -> 0.049074179 | G55: =G8/G54 -> 0.049074179 | H55: =H8/H54 -> 0.049074179 | I55: =I8/I54 -> 0.049074179 | J55: =J8/J54 -> 0.049074179 | K55: =K8/K54 -> 0.049074179 | L55: =L8/L54 -> 0.049074179 | ... T55: =T8/T54 -> 0.050618673 | Y55: =Y8/Y54 -> 0.078166603 | Z55: =Z8/Z54 -> 0.29260381 | AA55: =AA8/AA54 -> 0.15445719 | AB55: =AB8/AB54 -> 0.11520459 | AC55: =AC8/AC54 -> 0.053564127 | AD55: =AD8/AD54 -> 0.053564127 | AE55: =AE8/AE54 -> 0.076482566 | AF55: =AF8/AF54 -> 0.06267259 | ... BL55: =BL8/BL54 -> 0.062698116
C56: Receivables As % of LTM Rev | E56: =E9/E54 -> 0.15506077 | F56: =F9/F54 -> 0.15506077 | G56: =G9/G54 -> 0.15506077 | H56: =H9/H54 -> 0.15506077 | I56: =I9/I54 -> 0.15506077 | J56: =J9/J54 -> 0.15506077 | K56: =K9/K54 -> 0.15506077 | L56: =L9/L54 -> 0.15506077 | ... T56: =T9/T54 -> 0.1881583 | Y56: =Y9/Y54 -> 0.14777482 | Z56: =Z9/Z54 -> 0.17149654 | AA56: =AA9/AA54 -> 0.18075905 | AB56: =AB9/AB54 -> 0.13438019 | AC56: =AC9/AC54 -> 0.10331198 | AD56: =AD9/AD54 -> 0.10331198 | AE56: =AE9/AE54 -> 0.10180708 | AF56: =AF9/AF54 -> 0.11706087 | ... AX56: =AX9/AX54 -> 0.13052681 | AY56: =AX56 -> 0.13052681 | AZ56: =AY56 -> 0.13052681 | BA56: =AZ56 -> 0.13052681 | BB56: =BA56 -> 0.13052681 | BC56: =BC9/BC54 -> 0.13052681 | BD56: =AY56 -> 0.13052681 | BE56: =AZ56 -> 0.13052681 | BF56: =BA56 -> 0.13052681 | BG56: =BB56 -> 0.13052681 | BH56: =BH9/BH54 -> 0.13052681 | BI56: =BH56 -> 0.13052681 | BJ56: =BI56 -> 0.13052681 | BK56: =BJ56 -> 0.13052681 | BL56: =BK56 -> 0.13052681
C57: Prepaid As % of LTM Rev | E57: =E10/E54 -> 0.078041577 | F57: =F10/F54 -> 0.078041577 | G57: =G10/G54 -> 0.078041577 | H57: =H10/H54 -> 0.078041577 | I57: =I10/I54 -> 0.078041577 | J57: =J10/J54 -> 0.078041577 | K57: =K10/K54 -> 0.078041577 | L57: =L10/L54 -> 0.078041577 | ... T57: =T10/T54 -> 0.070457102 | Y57: =Y10/Y54 -> 0.070939521 | Z57: =Z10/Z54 -> 0.1699827 | AA57: =AA10/AA54 -> 0.20900265 | AB57: =AB10/AB54 -> 0.096934924 | AC57: =AC10/AC54 -> 0.13861251 | AD57: =AD10/AD54 -> 0.13861251 | AE57: =AE10/AE54 -> 0.16938152 | AF57: =AF10/AF54 -> 0.1313483 | ... AX57: =AX10/AX54 -> 0.091956726 | AY57: =AX57 -> 0.091956726 | AZ57: =AY57 -> 0.091956726 | BA57: =AZ57 -> 0.091956726 | BB57: =BA57 -> 0.091956726 | BC57: =BC10/BC54 -> 0.091956726 | BD57: =AY57 -> 0.091956726 | BE57: =AZ57 -> 0.091956726 | BF57: =BA57 -> 0.091956726 | BG57: =BB57 -> 0.091956726 | BH57: =BH10/BH54 -> 0.091956726 | BI57: =BH57 -> 0.091956726 | BJ57: =BI57 -> 0.091956726 | BK57: =BJ57 -> 0.091956726 | BL57: =BK57 -> 0.091956726
C58: Accounts payable as % of LTM Rev | E58: =E26/E54 -> 0.10746336 | F58: =F26/F54 -> 0.10746336 | G58: =G26/G54 -> 0.10746336 | H58: =H26/H54 -> 0.10746336 | I58: =I26/I54 -> 0.10746336 | J58: =J26/J54 -> 0.10746336 | K58: =K26/K54 -> 0.10746336 | L58: =L26/L54 -> 0.10746336 | ... T58: =T26/T54 -> 0.096431128 | Y58: =Y26/Y54 -> 0.079497908 | Z58: =Z26/Z54 -> 0.11483564 | AA58: =AA26/AA54 -> 0.13768756 | AB58: =AB26/AB54 -> 0.088479541 | AC58: =AC26/AC54 -> 0.077961019 | AD58: =AD26/AD54 -> 0.077961019 | AE58: =AE26/AE54 -> 0.08589972 | AF58: =AF26/AF54 -> 0.079121143 | ... AX58: =AX26/AX54 -> 0.10101129 | AY58: =AX58 -> 0.10101129 | AZ58: =AY58 -> 0.10101129 | BA58: =AZ58 -> 0.10101129 | BB58: =BA58 -> 0.10101129 | BC58: =BC26/BC54 -> 0.10101129 | BD58: =AY58 -> 0.10101129 | BE58: =AZ58 -> 0.10101129 | BF58: =BA58 -> 0.10101129 | BG58: =BB58 -> 0.10101129 | BH58: =BH26/BH54 -> 0.10101129 | BI58: =BH58 -> 0.10101129 | BJ58: =BI58 -> 0.10101129 | BK58: =BJ58 -> 0.10101129 | BL58: =BK58 -> 0.10101129
C59: Accrued liabilities as % of LTM rev | E59: =E27/E54 -> 0.10450983 | F59: =F27/F54 -> 0.10450983 | G59: =G27/G54 -> 0.10450983 | H59: =H27/H54 -> 0.10450983 | I59: =I27/I54 -> 0.10450983 | J59: =J27/J54 -> 0.10450983 | K59: =K27/K54 -> 0.10450983 | L59: =L27/L54 -> 0.10450983 | ... T59: =T27/T54 -> 0.10553226 | Y59: =Y27/Y54 -> 0.14435146 | Z59: =Z27/Z54 -> 0.17820069 | AA59: =AA27/AA54 -> 0.16681377 | AB59: =AB27/AB54 -> 0.13649404 | AC59: =AC27/AC54 -> 0.11762301 | AD59: =AD27/AD54 -> 0.11762301 | AE59: =AE27/AE54 -> 0.11949605 | AF59: =AF27/AF54 -> 0.12582543 | ... AX59: =AX27/AX54 -> 0.14475541 | AY59: =AX59 -> 0.14475541 | AZ59: =AY59 -> 0.14475541 | BA59: =AZ59 -> 0.14475541 | BB59: =BA59 -> 0.14475541 | BC59: =BC27/BC54 -> 0.14475541 | BD59: =AY59 -> 0.14475541 | BE59: =AZ59 -> 0.14475541 | BF59: =BA59 -> 0.14475541 | BG59: =BB59 -> 0.14475541 | BH59: =BH27/BH54 -> 0.14475541 | BI59: =BH59 -> 0.14475541 | BJ59: =BI59 -> 0.14475541 | BK59: =BJ59 -> 0.14475541 | BL59: =BK59 -> 0.14475541
C61: Leverage - Corporate Only
C62: LTM Adj. EBITDA | E62: =E282 -> 267 | F62: =F282 -> 267 | G62: =G282 -> 267 | H62: =H282 -> 267 | I62: =I282 -> 267 | J62: =J282 -> 267 | K62: =K282 -> 267 | L62: =L282 -> 267 | ... T62: =T282 -> 657 | Y62: =Y282 -> -1004 | Z62: =SUM(Z282,V282:X282) -> -759 | AA62: =SUM(Z282:AA282,W282:X282) -> 471 | AB62: =SUM(Z282:AB282,X282) -> 1361 | AC62: =SUM(Z282:AC282) -> 2129 | AD62: =AC62 -> 2129 | AE62: =SUM(AE282,AA282:AC282) -> 2742 | AF62: =SUM(AE282:AF282,AB282:AC282) -> 2868 | AG62: =SUM(AE282:AG282,AC282) -> 2623 | AH62: =SUM(AE282:AH282) -> 2305 | AI62: =AH62 -> 2305 | AJ62: =SUM(AJ282,AF282:AH282) -> 1928 | AK62: =SUM(AJ282:AK282,AG282:AH282) -> 1511 | AL62: =SUM(AJ282:AL282,AH282) -> 1252 | AM62: =SUM(AJ282:AM282) -> 561 | AN62: =AM62 -> 561 | AO62: =SUM(AO282,AK282:AM282) -> -243 | AP62: =SUM(AO282:AP282,AL282:AM282) -> -1050 | AQ62: =SUM(AO282:AQ282,AM282) -> -1566 | AR62: =SUM(AO282:AR282) -> -1541 | AS62: =AR62 -> -1541 | AT62: =SUM(AT282,AP282:AR282) -> -1299 | AU62: =SUM(AT282:AU282,AQ282:AR282) -> -838 | AV62: =SUM(AT282:AV282,AR282) -> -491 | AW62: =SUM(AT282:AW282) -> -339 | AX62: =AW62 -> -339 | AY62: =SUM(AY282,AU282:AW282) -> -170.83204 | AZ62: =SUM(AY282:AZ282,AV282:AW282) -> -93.306223 | BA62: =SUM(AY282:BA282,AW282) -> -25.402164 | BB62: =SUM(AY282:BB282) -> 71.170039 | BC62: =BB62 -> 71.170039 | BD62: =SUM(BD282,AZ282:BB282) -> 88.50956 | BE62: =SUM(BD282:BE282,BA282:BB282) -> 112.22388 | BF62: =SUM(BD282:BF282,BB282) -> 140.25341 | BG62: =SUM(BD282:BG282) -> 159.88912 | BH62: =BH282 -> 159.88912 | BI62: =BI282 -> 301.72063 | BJ62: =BJ282 -> 434.46001 | BK62: =BK282 -> 575.08334 | BL62: =BL282 -> 717.1677
C64: 1st Lien Debt | E64: 688 | F64: 688 | G64: 688 | H64: 688 | I64: 688 | J64: 688 | K64: 688 | L64: 688 | M64: 688 | N64: 688 | O64: 688 | P64: 688 | Q64: 688 | R64: 688 | S64: =674 -> 674 | T64: 660 | Y64: 250 | Z64: 750 | AA64: =1300+245 -> 1545 | AB64: =1297+245 -> 1542 | AC64: =1294+245 -> 1539 | AD64: =AC64 -> 1539 | AE64: =1290+245 -> 1535 | AF64: =1287+245 -> 1532 | AG64: =1284+245 -> 1529 | AH64: =1281+245 -> 1526 | AI64: =AH64 -> 1526 | AJ64: =1277+245 -> 1522 | AK64: =1274+245+500 -> 2019 | AL64: =1271+245+150 -> 1666 | AM64: =1268+500+245 -> 2013 | AN64: =AM64 -> 2013 | AO64: =450+1264+499+245 -> 2458 | AP64: =160+1261+498+245+750 -> 2914 | AQ64: =250+1258+496+245+750 -> 2999 | AR64: =175+1255+495+245+1250 -> 3420 | AS64: =AR64 -> 3420 | AT64: =800+1251+494+245+1250 -> 4040 | AU64: =375+1248+493+245+1250 -> 3611 | AV64: =210+1245+491+245+1250 -> 3441 | AW64: =395+346+1242+490+245+1250 -> 3968 | AX64: =AW64 -> 3968 | AY64: =SUM(AY291:AY295) -> 3503.8238 | AZ64: =SUM(AZ291:AZ295) -> 3092.8907 | BA64: =SUM(BA291:BA295) -> 2442.3915 | BB64: =SUM(BB291:BB295) -> 2340.5977 | BC64: =BB64 -> 2340.5977 | BD64: =SUM(BD291:BD295) -> 2081.2294 | BE64: =SUM(BE291:BE295) -> 1605.237 | BF64: =SUM(BF291:BF295) -> 883.03749 | BG64: =SUM(BG291:BG295) -> 515.72358 | BH64: =BG64 -> 515.72358 | BI64: =SUM(BI291:BI295) -> -1662.2509 | BJ64: =SUM(BJ291:BJ295) -> -4206.6445 | BK64: =SUM(BK291:BK295) -> -7160.2911 | BL64: =SUM(BL291:BL295) -> -10560.306
C65: 2nd Lien Debt | E65: 1250 | F65: 1250 | G65: 1250 | H65: 1250 | I65: 1250 | J65: 1250 | K65: 1250 | L65: 1250 | M65: 1250 | N65: 1250 | O65: 1250 | P65: 1250 | Q65: 1250 | R65: 1250 | S65: 1250 | T65: 350 | Y65: 0 | Z65: 0 | AA65: 0 | AB65: 0 | AC65: 0 | AD65: =AC65 -> 0 | AE65: 0 | AF65: 0 | AG65: 0 | AH65: 0 | AI65: =AH65 -> 0 | AJ65: 0 | AK65: 0 | AL65: 0 | AM65: 0 | AN65: =AM65 -> 0 | AO65: 0 | AP65: 0 | AQ65: 250 | AR65: 250 | AS65: =AR65 -> 250 | AT65: 261 | AU65: 261 | AV65: 271 | AW65: 271 | AX65: =AW65 -> 271 | AY65: =AY296 -> 281.84 | AZ65: =AZ296 -> 281.84 | BA65: =BA296 -> 293.1136 | BB65: =BB296 -> 293.1136 | BC65: =BB65 -> 293.1136 | BD65: =BD296 -> 304.83814 | BE65: =BE296 -> 304.83814 | BF65: =BF296 -> 317.03167 | BG65: =BG296 -> 317.03167 | BH65: =BG65 -> 317.03167 | BI65: =BI296 -> 342.3942 | BJ65: =BJ296 -> 369.78574 | BK65: =BK296 -> 399.3686 | BL65: =BL296 -> 431.31809
C66: Unsecured Debt | E66: =2500+27+11 -> 2538 | F66: =2500+27+11 -> 2538 | G66: =2500+27+11 -> 2538 | H66: =2500+27+11 -> 2538 | I66: =2500+27+11 -> 2538 | J66: =2500+27+11 -> 2538 | K66: =2500+27+11 -> 2538 | L66: =2500+27+11 -> 2538 | ... R66: =2500+27+11 -> 2538 | S66: =2500+27+4 -> 2531 | T66: =2700+27+18 -> 2745 | Y66: 18 | Z66: 16 | AA66: 15 | AB66: 14 | AC66: =1516 -> 1516 | AD66: =AC66 -> 1516 | AE66: =1500+15 -> 1515 | AF66: 1513 | AG66: 1512 | AH66: 1509 | AI66: =AH66 -> 1509 | AJ66: 1508 | AK66: 1504 | AL66: 1504 | AM66: 1502 | AN66: =AM66 -> 1502 | AO66: 1502 | AP66: 1521 | AQ66: 1502 | AR66: 1500 | AS66: =AR66 -> 1500 | AT66: 1500 | AU66: 1506 | AV66: =425+500+1000+6 -> 1931 | AW66: =425+200+1000+6 -> 1631 | AX66: =AW66 -> 1631 | AY66: =SUM(AY297:AY301) -> 1631 | AZ66: =SUM(AZ297:AZ301) -> 1631 | BA66: =SUM(BA297:BA301) -> 1631 | BB66: =SUM(BB297:BB301) -> 1431 | BC66: =BB66 -> 1431 | BD66: =SUM(BD297:BD301) -> 1431 | BE66: =SUM(BE297:BE301) -> 1431 | BF66: =SUM(BF297:BF301) -> 1431 | BG66: =SUM(BG297:BG301) -> 1431 | BH66: =BG66 -> 1431 | BI66: =SUM(BI297:BI301) -> 1431 | BJ66: =SUM(BJ297:BJ301) -> 1431 | BK66: =SUM(BK297:BK301) -> 1431 | BL66: =SUM(BL297:BL301) -> 1431
C67: Total | E67: =SUM(E64:E66) -> 4476 | F67: =SUM(F64:F66) -> 4476 | G67: =SUM(G64:G66) -> 4476 | H67: =SUM(H64:H66) -> 4476 | I67: =SUM(I64:I66) -> 4476 | J67: =SUM(J64:J66) -> 4476 | K67: =SUM(K64:K66) -> 4476 | L67: =SUM(L64:L66) -> 4476 | ... T67: =SUM(T64:T66) -> 3755 | Y67: =SUM(Y64:Y66) -> 268 | Z67: =SUM(Z64:Z66) -> 766 | AA67: =SUM(AA64:AA66) -> 1560 | AB67: =SUM(AB64:AB66) -> 1556 | AC67: =SUM(AC64:AC66) -> 3055 | AD67: =AC67 -> 3055 | AE67: =SUM(AE64:AE66) -> 3050 | AF67: =SUM(AF64:AF66) -> 3045 | AG67: =SUM(AG64:AG66) -> 3041 | AH67: =SUM(AH64:AH66) -> 3035 | AI67: =AH67 -> 3035 | AJ67: =SUM(AJ64:AJ66) -> 3030 | AK67: =SUM(AK64:AK66) -> 3523 | AL67: =SUM(AL64:AL66) -> 3170 | AM67: =SUM(AM64:AM66) -> 3515 | AN67: =AM67 -> 3515 | AO67: =SUM(AO64:AO66) -> 3960 | AP67: =SUM(AP64:AP66) -> 4435 | AQ67: =SUM(AQ64:AQ66) -> 4751 | AR67: =SUM(AR64:AR66) -> 5170 | AS67: =AR67 -> 5170 | AT67: =SUM(AT64:AT66) -> 5801 | AU67: =SUM(AU64:AU66) -> 5378 | AV67: =SUM(AV64:AV66) -> 5643 | AW67: =SUM(AW64:AW66) -> 5870 | AX67: =AW67 -> 5870 | AY67: =SUM(AY64:AY66) -> 5416.6638 | AZ67: =SUM(AZ64:AZ66) -> 5005.7307 | BA67: =SUM(BA64:BA66) -> 4366.5051 | BB67: =SUM(BB64:BB66) -> 4064.7113 | BC67: =BB67 -> 4064.7113 | BD67: =SUM(BD64:BD66) -> 3817.0675 | BE67: =SUM(BE64:BE66) -> 3341.0751 | BF67: =SUM(BF64:BF66) -> 2631.0692 | BG67: =SUM(BG64:BG66) -> 2263.7553 | BH67: =BG67 -> 2263.7553 | BI67: =SUM(BI64:BI66) -> 111.14329 | BJ67: =SUM(BJ64:BJ66) -> -2405.8587 | BK67: =SUM(BK64:BK66) -> -5329.9226 | BL67: =SUM(BL64:BL66) -> -8697.9881
C69: Net 1st Lien / Adj. EBITDA | E69: =(SUM(E$64:E64)-E$7)/E$62 -> -1.4382022 | F69: =(SUM(F$64:F64)-F$7)/F$62 -> -1.4382022 | G69: =(SUM(G$64:G64)-G$7)/G$62 -> -1.4382022 | H69: =(SUM(H$64:H64)-H$7)/H$62 -> -1.4382022 | I69: =(SUM(I$64:I64)-I$7)/I$62 -> -1.4382022 | J69: =(SUM(J$64:J64)-J$7)/J$62 -> -1.4382022 | K69: =(SUM(K$64:K64)-K$7)/K$62 -> -1.4382022 | L69: =(SUM(L$64:L64)-L$7)/L$62 -> -1.4382022 | ... T69: =(SUM(T$64:T64)-T$7)/T$62 -> -0.31202435 | Y69: =(SUM(Y$64:Y64)-Y$7)/Y$62 -> 0.84262948 | Z69: =(SUM(Z$64:Z64)-Z$7)/Z$62 -> 0.44400527 | AA69: =(SUM(AA$64:AA64)-AA$7)/AA$62 -> -0.58386412 | AB69: =(SUM(AB$64:AB64)-AB$7)/AB$62 -> -0.85304923 | AC69: =(SUM(AC$64:AC64)-AC$7)/AC$62 -> -0.33771724 | AD69: =(SUM(AD$64:AD64)-AD$7)/AD$62 -> -0.33771724 | AE69: =(SUM(AE$64:AE64)-AE$7)/AE$62 -> 0.0051057622 | AF69: =(SUM(AF$64:AF64)-AF$7)/AF$62 -> 0.17119944 | ... BL69: =(SUM(BL$64:BL64)-BL$7)/BL$62 -> -15.143329
C70: Net 2nd Lien / Adj. EBITDA | E70: =(SUM(E$64:E65)-E$7)/E$62 -> 3.2434457 | F70: =(SUM(F$64:F65)-F$7)/F$62 -> 3.2434457 | G70: =(SUM(G$64:G65)-G$7)/G$62 -> 3.2434457 | H70: =(SUM(H$64:H65)-H$7)/H$62 -> 3.2434457 | I70: =(SUM(I$64:I65)-I$7)/I$62 -> 3.2434457 | J70: =(SUM(J$64:J65)-J$7)/J$62 -> 3.2434457 | K70: =(SUM(K$64:K65)-K$7)/K$62 -> 3.2434457 | L70: =(SUM(L$64:L65)-L$7)/L$62 -> 3.2434457 | ... T70: =(SUM(T$64:T65)-T$7)/T$62 -> 0.22070015 | Y70: =(SUM(Y$64:Y65)-Y$7)/Y$62 -> 0.84262948 | Z70: =(SUM(Z$64:Z65)-Z$7)/Z$62 -> 0.44400527 | AA70: =(SUM(AA$64:AA65)-AA$7)/AA$62 -> -0.58386412 | AB70: =(SUM(AB$64:AB65)-AB$7)/AB$62 -> -0.85304923 | AC70: =(SUM(AC$64:AC65)-AC$7)/AC$62 -> -0.33771724 | AD70: =(SUM(AD$64:AD65)-AD$7)/AD$62 -> -0.33771724 | AE70: =(SUM(AE$64:AE65)-AE$7)/AE$62 -> 0.0051057622 | AF70: =(SUM(AF$64:AF65)-AF$7)/AF$62 -> 0.17119944 | ... BL70: =(SUM(BL$64:BL65)-BL$7)/BL$62 -> -14.54191
C71: Net Total Debt / Adj. EBITDA | E71: =(SUM(E$64:E66)-E$7)/E$62 -> 12.749064 | F71: =(SUM(F$64:F66)-F$7)/F$62 -> 12.749064 | G71: =(SUM(G$64:G66)-G$7)/G$62 -> 12.749064 | H71: =(SUM(H$64:H66)-H$7)/H$62 -> 12.749064 | I71: =(SUM(I$64:I66)-I$7)/I$62 -> 12.749064 | J71: =(SUM(J$64:J66)-J$7)/J$62 -> 12.749064 | K71: =(SUM(K$64:K66)-K$7)/K$62 -> 12.749064 | L71: =(SUM(L$64:L66)-L$7)/L$62 -> 12.749064 | ... T71: =(SUM(T$64:T66)-T$7)/T$62 -> 4.3987823 | Y71: =(SUM(Y$64:Y66)-Y$7)/Y$62 -> 0.8247012 | Z71: =(SUM(Z$64:Z66)-Z$7)/Z$62 -> 0.4229249 | AA71: =(SUM(AA$64:AA66)-AA$7)/AA$62 -> -0.55201699 | AB71: =(SUM(AB$64:AB66)-AB$7)/AB$62 -> -0.84276267 | AC71: =(SUM(AC$64:AC66)-AC$7)/AC$62 -> 0.37435416 | AD71: =(SUM(AD$64:AD66)-AD$7)/AD$62 -> 0.37435416 | AE71: =(SUM(AE$64:AE66)-AE$7)/AE$62 -> 0.55762217 | AF71: =(SUM(AF$64:AF66)-AF$7)/AF$62 -> 0.69874477 | ... BL71: =(SUM(BL$64:BL66)-BL$7)/BL$62 -> -12.546561
B75: Income statement
B77: Americas RAC | E77: =E5 -> 2004 | F77: =F5 -> 2005 | G77: =G5 -> 2006 | H77: =H5 -> 2007 | I77: =I5 -> 2008 | J77: =J5 -> 2009 | K77: =K5 -> 2010 | L77: =L5 -> 2011 | ... BL77: =BL5 -> 2031
C79: Net Revenue | E79: 5994 | F79: 5994 | G79: 5994 | H79: 5994 | I79: 5994 | J79: 5994 | K79: 5994 | L79: 5994 | M79: 5994 | N79: 5994 | O79: 5994 | P79: 5994 | Q79: 5994 | R79: 5994 | S79: 6480 | T79: 6938 | U79: 1381 | V79: 533 | W79: 866 | X79: 876 | Y79: =SUM(U79:X79) -> 3656 | Z79: 967 | AA79: 1643 | AB79: 1914 | AC79: 1691 | AD79: =SUM(Z79:AC79) -> 6215 | AE79: 1558 | AF79: 1973 | AG79: 2042 | AH79: 1707 | AI79: =SUM(AE79:AH79) -> 7280 | AJ79: 1730 | AK79: 2015 | AL79: 2172 | AM79: 1805 | AN79: =SUM(AJ79:AM79) -> 7722 | AO79: 1739 | AP79: 1928 | AQ79: 2062 | AR79: 1669 | AS79: =SUM(AO79:AR79) -> 7398 | AT79: 1490 | AU79: 1738 | AV79: 1910 | AW79: 1621 | AX79: =SUM(AT79:AW79) -> 6759 | AY79: =AY86*AY90/1000 -> 1539.0089 | AZ79: =AZ86*AZ90/1000 -> 1791.0808 | BA79: =BA86*BA90/1000 -> 1985.6761 | BB79: =BB86*BB90/1000 -> 1689.063 | BC79: =SUM(AY79:BB79) -> 7004.8289 | BD79: =BD86*BD90/1000 -> 1569.7891 | BE79: =BE86*BE90/1000 -> 1826.9025 | BF79: =BF86*BF90/1000 -> 2025.3897 | BG79: =BG86*BG90/1000 -> 1722.8442 | BH79: =SUM(BD79:BG79) -> 7144.9255 | BI79: =BI86*BI90/1000 -> 7306.4866 | BJ79: =BJ86*BJ90/1000 -> 7432.254 | BK79: =BK86*BK90/1000 -> 7580.8991 | BL79: =BL86*BL90/1000 -> 7732.517
C80: Growth | S80: =S79/R79-1 -> 0.081081081 | T80: =T79/S79-1 -> 0.070679012 | Y80: =Y79/T79-1 -> -0.47304699 | AE80: =AE79/Z79-1 -> 0.61116856 | AF80: =AF79/AA79-1 -> 0.2008521 | AG80: =AG79/AB79-1 -> 0.066875653 | AH80: =AH79/AC79-1 -> 0.0094618569 | AI80: =AI79/AD79-1 -> 0.17135961 | AJ80: =AJ79/AE79-1 -> 0.11039795 | AK80: =AK79/AF79-1 -> 0.02128738 | AL80: =AL79/AG79-1 -> 0.063663075 | ... BH80: =BH79/BC79-1 -> 0.02 | BI80: =BI79/BH79-1 -> 0.022612009 | BJ80: =BJ79/BI79-1 -> 0.017213115 | BK80: =BK79/BJ79-1 -> 0.02 | BL80: =BL79/BK79-1 -> 0.02
C82: Foreign Currency Adjustments | E82: 0 | F82: 0 | G82: 0 | H82: 0 | I82: 0 | J82: 0 | K82: 0 | L82: 0 | M82: 0 | N82: 0 | O82: 0 | P82: 0 | Q82: 0 | R82: 0 | S82: 0 | T82: 0 | U82: 0 | V82: 0 | W82: 0 | X82: 0 | Y82: =SUM(U82:X82) -> 0 | Z82: 0 | AA82: -1 | AB82: 0 | AC82: 0 | AD82: =SUM(Z82:AC82) -> -1 | AE82: -2 | AF82: -4 | AG82: -6 | AH82: 0 | AI82: =SUM(AE82:AH82) -> -12 | AJ82: -1 | AK82: -1 | AL82: -1 | AM82: 0 | AN82: =SUM(AJ82:AM82) -> -3 | AO82: -4 | AP82: -4 | AQ82: -6 | AR82: -2 | AS82: =SUM(AO82:AR82) -> -16 | AT82: 0 | AU82: -3 | AV82: -5 | AW82: -2 | AX82: =SUM(AT82:AW82) -> -10 | AY82: 0 | AZ82: 0 | BA82: 0 | BB82: 0 | BC82: =SUM(AY82:BB82) -> 0 | BD82: 0 | BE82: 0 | BF82: 0 | BG82: 0 | BH82: =SUM(BD82:BG82) -> 0 | BI82: 0 | BJ82: 0 | BK82: 0 | BL82: 0
C83: Foreign Currency Adjustments - on depreciation | E83: 0 | F83: 0 | G83: 0 | H83: 0 | I83: 0 | J83: 0 | K83: 0 | L83: 0 | M83: 0 | N83: 0 | O83: 0 | P83: 0 | Q83: 0 | R83: 0 | S83: 0 | T83: 0 | U83: 0 | V83: 0 | W83: 0 | X83: 0 | Y83: =SUM(U83:X83) -> 0 | Z83: 0 | AA83: 1 | AB83: 0 | AC83: 0 | AD83: =SUM(Z83:AC83) -> 1 | AE83: 0 | AF83: 1 | AG83: 1 | AH83: 0 | AI83: =SUM(AE83:AH83) -> 2 | AJ83: 1 | AK83: 0 | AL83: 1 | AM83: 0 | AN83: =SUM(AJ83:AM83) -> 2 | AO83: 0 | AP83: -1 | AQ83: -1 | AR83: 0 | AS83: =SUM(AO83:AR83) -> -2 | AT83: 0 | AU83: -1 | AV83: 0 | AW83: 0 | AX83: =SUM(AT83:AW83) -> -1 | AY83: 0 | AZ83: 0 | BA83: 0 | BB83: 0 | BC83: =SUM(AY83:BB83) -> 0 | BD83: 0 | BE83: 0 | BF83: 0 | BG83: 0 | BH83: =SUM(BD83:BG83) -> 0 | BI83: 0 | BJ83: 0 | BK83: 0 | BL83: 0
C84: Number of Days in Period | E84: 365 | F84: 365 | G84: 365 | H84: 365 | I84: 365 | J84: 365 | K84: 365 | L84: 365 | M84: 365 | N84: 365 | O84: 365 | P84: 365 | Q84: 365 | R84: 365 | S84: 365 | T84: 365 | U84: 91 | V84: 91 | W84: 92 | X84: 92 | Y84: =SUM(U84:X84) -> 366 | Z84: 90 | AA84: 91 | AB84: 92 | AC84: 92 | AD84: =SUM(Z84:AC84) -> 365 | AE84: 90 | AF84: 91 | AG84: 92 | AH84: 92 | AI84: =SUM(AE84:AH84) -> 365 | AJ84: 90 | AK84: 91 | AL84: 92 | AM84: 92 | AN84: =SUM(AJ84:AM84) -> 365 | AO84: 91 | AP84: 91 | AQ84: 92 | AR84: 92 | AS84: =SUM(AO84:AR84) -> 366 | AT84: 90 | AU84: 91 | AV84: 92 | AW84: 92 | AX84: =SUM(AT84:AW84) -> 365 | AY84: 90 | AZ84: 91 | BA84: 92 | BB84: 92 | BC84: =SUM(AY84:BB84) -> 365 | BD84: 90 | BE84: 91 | BF84: 92 | BG84: 92 | BH84: =SUM(BD84:BG84) -> 365 | BI84: 366 | BJ84: 365 | BK84: 365 | BL84: 365
C85: Available Car Day | E85: =E84*E88/1000 -> 176915.5 | F85: =F84*F88/1000 -> 176915.5 | G85: =G84*G88/1000 -> 176915.5 | H85: =H84*H88/1000 -> 176915.5 | I85: =I84*I88/1000 -> 176915.5 | J85: =J84*J88/1000 -> 176915.5 | K85: =K84*K88/1000 -> 176915.5 | L85: =L84*L88/1000 -> 176915.5 | ... X85: =X84*X88/1000 -> 27432.836 | Y85: =SUM(U85:X85) -> 155007.8 | Z85: =Z84*Z88/1000 -> 26677.08 | AA85: =AA84*AA88/1000 -> 31317.65 | AB85: =AB84*AB88/1000 -> 34253.992 | AC85: =AC84*AC88/1000 -> 33895.928 | AD85: =SUM(Z85:AC85) -> 126144.65 | AE85: =AE84*AE88/1000 -> 33583.77 | AF85: =AF84*AF88/1000 -> 36362.508 | AG85: =AG84*AG88/1000 -> 36568.896 | AH85: =AH84*AH88/1000 -> 34106.516 | AI85: =SUM(AE85:AH85) -> 140621.69 | AJ85: =AJ84*AJ88/1000 -> 35416.08 | AK85: =AK84*AK88/1000 -> 39304.811 | AL85: =AL84*AL88/1000 -> 40696.476 | AM85: =AM84*AM88/1000 -> 38838.26 | AN85: =SUM(AJ85:AM85) -> 154255.63 | AO85: =AO84*AO88/1000 -> 39477.893 | AP85: =AP84*AP88/1000 -> 39974.844 | AQ85: =AQ84*AQ88/1000 -> 39799.936 | AR85: =AR84*AR88/1000 -> 36793.284 | AS85: =SUM(AO85:AR85) -> 156045.96 | AT85: =AT84*AT88/1000 -> 34808.13 | AU85: =AU84*AU88/1000 -> 37067.576 | AV85: =AV84*AV88/1000 -> 37648.424 | AW85: =AW84*AW88/1000 -> 36625.752 | AX85: =SUM(AT85:AW85) -> 146149.88 | AY85: =AY84*AY88/1000 -> 35156.211 | AZ85: =AZ84*AZ88/1000 -> 37438.252 | BA85: =BA84*BA88/1000 -> 38401.392 | BB85: =BB84*BB88/1000 -> 37358.267 | BC85: =SUM(AY85:BB85) -> 148354.12 | BD85: =BD84*BD88/1000 -> 35859.336 | BE85: =BE84*BE88/1000 -> 38187.017 | BF85: =BF84*BF88/1000 -> 39169.42 | BG85: =BG84*BG88/1000 -> 38105.432 | BH85: =SUM(BD85:BG85) -> 151321.21 | BI85: =BI84*BI88/1000 -> 154742.88 | BJ85: =BJ84*BJ88/1000 -> 157406.49 | BK85: =BK84*BK88/1000 -> 160554.62 | BL85: =BL84*BL88/1000 -> 163765.71
C86: Transaction Days (in thousands) | E86: 140382 | F86: 140382 | G86: 140382 | H86: 140382 | I86: 140382 | J86: 140382 | K86: 140382 | L86: 140382 | M86: 140382 | N86: 140382 | O86: 140382 | P86: 140382 | Q86: 140382 | R86: 140382 | S86: 149463 | T86: 155859 | U86: 31564 | V86: 12964 | W86: 17971 | X86: 20178 | Y86: =SUM(U86:X86) -> 82677 | Z86: 20251 | AA86: 24992 | AB86: 27627 | AC86: 27215 | AD86: =SUM(Z86:AC86) -> 100085 | AE86: 25579 | AF86: 29160 | AG86: 29653 | AH86: 27367 | AI86: =SUM(AE86:AH86) -> 111759 | AJ86: 27879 | AK86: 32469 | AL86: 34278 | AM86: 30589 | AN86: =SUM(AJ86:AM86) -> 125215 | AO86: 30560 | AP86: 32216 | AQ86: 32693 | AR86: 29298 | AS86: =SUM(AO86:AR86) -> 124767 | AT86: 27758 | AU86: 30935 | AV86: 31923 | AW86: 28857 | AX86: =SUM(AT86:AW86) -> 119473 | AY86: =AY85*AY89 -> 28387.142 | AZ86: =AZ85*AZ89 -> 31618.733 | BA86: =BA85*BA89 -> 32945.474 | BB86: =BB85*BB89 -> 29807.723 | BC86: =SUM(AY86:BB86) -> 122759.07 | BD86: =BD85*BD89 -> 28954.885 | BE86: =BE85*BE89 -> 32251.107 | BF86: =BF85*BF89 -> 33604.383 | BG86: =BG85*BG89 -> 30403.877 | BH86: =SUM(BD86:BG86) -> 125214.25 | BI86: =BI85*BI89 -> 128045.6 | BJ86: =BJ85*BJ89 -> 130249.66 | BK86: =BK85*BK89 -> 132854.66 | BL86: =BL85*BL89 -> 135511.75
C87: Average Vehicles (in whole units) | E87: 484700 | F87: 484700 | G87: 484700 | H87: 484700 | I87: 484700 | J87: 484700 | K87: 484700 | L87: 484700 | M87: 484700 | N87: 484700 | O87: 484700 | P87: 484700 | Q87: 484700 | R87: 484700 | S87: 506900 | T87: 534879 | U87: 518580 | V87: 502763 | W87: 376443 | X87: 298183 | Y87: =AVERAGE(U87:X87) -> 423992.25 | Z87: 300606 | AA87: 350122 | AB87: 387368 | AC87: 384492 | AD87: =AVERAGE(Z87:AC87) -> 355647 | AE87: 397620 | AF87: 422113 | AG87: 425596 | AH87: 398860 | AI87: =AVERAGE(AE87:AH87) -> 411047.25 | AJ87: 412983 | AK87: 457405 | AL87: 467916 | AM87: 446573 | AN87: =AVERAGE(AJ87:AM87) -> 446219.25 | AO87: 450585 | AP87: 467863 | AQ87: 463467 | AR87: 432909 | AS87: =AVERAGE(AO87:AR87) -> 453706 | AT87: 413381 | AU87: 435737 | AV87: 425004 | AW87: 415264 | AX87: =AVERAGE(AT87:AW87) -> 422346.5 | AY87: =AT87/AT88*AY88 -> 417514.81 | AZ87: =AU87/AU88*AZ88 -> 440094.37 | BA87: =AV87/AV88*BA88 -> 433504.08 | BB87: =AW87/AW88*BB88 -> 423569.28 | BC87: =AVERAGE(AY87:BB87) -> 428670.64 | BD87: =AY87/AY88*BD88 -> 425865.11 | BE87: =AZ87/AZ88*BE88 -> 448896.26 | BF87: =BA87/BA88*BF88 -> 442174.16 | BG87: =BB87/BB88*BG88 -> 432040.67 | BH87: =AVERAGE(BD87:BG87) -> 437244.05 | BI87: =BH87/BH88*BI88 -> 445988.93 | BJ87: =BI87/BI88*BJ88 -> 454908.71 | BK87: =BJ87/BJ88*BK88 -> 464006.88 | BL87: =BK87/BK88*BL88 -> 473287.02
C88: Average Rentable Vehicles (in whole units) | E88: 484700 | F88: 484700 | G88: 484700 | H88: 484700 | I88: 484700 | J88: 484700 | K88: 484700 | L88: 484700 | M88: 484700 | N88: 484700 | O88: 484700 | P88: 484700 | Q88: 484700 | R88: 484700 | S88: 506900 | T88: 534879 | U88: 518580 | V88: 502763 | W88: 376443 | X88: 298183 | Y88: =AVERAGE(U88:X88) -> 423992.25 | Z88: 296412 | AA88: 344150 | AB88: 372326 | AC88: 368434 | AD88: =AVERAGE(Z88:AC88) -> 345330.5 | AE88: 373153 | AF88: 399588 | AG88: 397488 | AH88: 370723 | AI88: =AVERAGE(AE88:AH88) -> 385238 | AJ88: 393512 | AK88: 431921 | AL88: 442353 | AM88: 422155 | AN88: =AVERAGE(AJ88:AM88) -> 422485.25 | AO88: 433823 | AP88: 439284 | AQ88: 432608 | AR88: 399927 | AS88: =AVERAGE(AO88:AR88) -> 426410.5 | AT88: 386757 | AU88: 407336 | AV88: 409222 | AW88: 398106 | AX88: =AVERAGE(AT88:AW88) -> 400355.25 | AY88: =AT88*(1+AY104) -> 390624.57 | AZ88: =AU88*(1+AZ104) -> 411409.36 | BA88: =AV88*(1+BA104) -> 417406.44 | BB88: =AW88*(1+BB104) -> 406068.12 | BC88: =AVERAGE(AY88:BB88) -> 406377.12 | BD88: =AY88*(1+BD104) -> 398437.06 | BE88: =AZ88*(1+BE104) -> 419637.55 | BF88: =BA88*(1+BF104) -> 425754.57 | BG88: =BB88*(1+BG104) -> 414189.48 | BH88: =AVERAGE(BD88:BG88) -> 414504.66 | BI88: =BH88*(1+BI104) -> 422794.76 | BJ88: =BI88*(1+BJ104) -> 431250.65 | BK88: =BJ88*(1+BK104) -> 439875.67 | BL88: =BK88*(1+BL104) -> 448673.18
C89: Vehicle Utilization | E89: =E86/E85 -> 0.79349746 | F89: =F86/F85 -> 0.79349746 | G89: =G86/G85 -> 0.79349746 | H89: =H86/H85 -> 0.79349746 | I89: =I86/I85 -> 0.79349746 | J89: =J86/J85 -> 0.79349746 | K89: =K86/K85 -> 0.79349746 | L89: =L86/L85 -> 0.79349746 | ... AX89: =AX86/AX85 -> 0.81746901 | AY89: =AT89+0.01 -> 0.80745738 | AZ89: =AU89+0.01 -> 0.84455686 | BA89: =AV89+0.01 -> 0.85792394 | BB89: =AW89+0.01 -> 0.79788826 | BC89: =BC86/BC85 -> 0.82747327 | BD89: =AY89 -> 0.80745738 | BE89: =AZ89 -> 0.84455686 | BF89: =BA89 -> 0.85792394 | BG89: =BB89 -> 0.79788826 | BH89: =BH86/BH85 -> 0.82747327 | BI89: =BH89 -> 0.82747327 | BJ89: =BI89 -> 0.82747327 | BK89: =BJ89 -> 0.82747327 | BL89: =BK89 -> 0.82747327
C90: Total RPD (in dollars) | E90: =(E79+E82)/E86*1000 -> 42.697782 | F90: =(F79+F82)/F86*1000 -> 42.697782 | G90: =(G79+G82)/G86*1000 -> 42.697782 | H90: =(H79+H82)/H86*1000 -> 42.697782 | I90: =(I79+I82)/I86*1000 -> 42.697782 | J90: =(J79+J82)/J86*1000 -> 42.697782 | K90: =(K79+K82)/K86*1000 -> 42.697782 | L90: =(L79+L82)/L86*1000 -> 42.697782 | ... AX90: =(AX79+AX82)/AX86*1000 -> 56.489751 | AY90: =AT90*(1+AY106) -> 54.215001 | AZ90: =AU90*(1+AZ106) -> 56.646194 | BA90: =AV90*(1+BA106) -> 60.271591 | BB90: =AW90*(1+BB106) -> 56.665281 | BC90: =(BC79+BC82)/BC86*1000 -> 57.061599 | BD90: =AY90*(1+BD106) -> 54.215001 | BE90: =AZ90*(1+BE106) -> 56.646194 | BF90: =BA90*(1+BF106) -> 60.271591 | BG90: =BB90*(1+BG106) -> 56.665281 | BH90: =(BH79+BH82)/BH86*1000 -> 57.061599 | BI90: =BH90*(1+BI106) -> 57.061599 | BJ90: =BI90*(1+BJ106) -> 57.061599 | BK90: =BJ90*(1+BK106) -> 57.061599 | BL90: =BK90*(1+BL106) -> 57.061599
C91: Total RPU Per Month (in whole dollars) | E91: =(E79+E82)/E88/12*1000000 -> 1030.5344 | F91: =(F79+F82)/F88/12*1000000 -> 1030.5344 | G91: =(G79+G82)/G88/12*1000000 -> 1030.5344 | H91: =(H79+H82)/H88/12*1000000 -> 1030.5344 | I91: =(I79+I82)/I88/12*1000000 -> 1030.5344 | J91: =(J79+J82)/J88/12*1000000 -> 1030.5344 | K91: =(K79+K82)/K88/12*1000000 -> 1030.5344 | L91: =(L79+L82)/L88/12*1000000 -> 1030.5344 | ... T91: =(T79+T82)/T88/12*1000000 -> 1080.9298 | U91: =(U79+U82)/U88/3*1000000 -> 887.68046 | V91: =(V79+V82)/V88/3*1000000 -> 353.38055 | W91: =(W79+W82)/W88/3*1000000 -> 766.82703 | X91: =(X79+X82)/X88/3*1000000 -> 979.26441 | Y91: =(Y79+Y82)/Y88/12*1000000 -> 718.56659 | Z91: =(Z79+Z82)/Z88/3*1000000 -> 1087.4504 | AA91: =(AA79+AA82)/AA88/3*1000000 -> 1590.3918 | AB91: =(AB79+AB82)/AB88/3*1000000 -> 1713.5521 | AC91: =(AC79+AC82)/AC88/3*1000000 -> 1529.8986 | AD91: =(AD79+AD82)/AD88/12*1000000 -> 1499.5297 | AE91: =(AE79+AE82)/AE88/3*1000000 -> 1389.9571 | AF91: =(AF79+AF82)/AF88/3*1000000 -> 1642.5251 | AG91: =(AG79+AG82)/AG88/3*1000000 -> 1707.3891 | AH91: =(AH79+AH82)/AH88/3*1000000 -> 1534.8387 | AI91: =(AI79+AI82)/AI88/12*1000000 -> 1572.1883 | AJ91: =(AJ79+AJ82)/AJ88/3*1000000 -> 1464.589 | AK91: =(AK79+AK82)/AK88/3*1000000 -> 1554.2966 | AL91: =(AL79+AL82)/AL88/3*1000000 -> 1635.9484 | AM91: =(AM79+AM82)/AM88/3*1000000 -> 1425.2269 | AN91: =(AN79+AN82)/AN88/12*1000000 -> 1522.5384 | AO91: =(AO79+AO82)/AO88/3*1000000 -> 1333.109 | AP91: =(AP79+AP82)/AP88/3*1000000 -> 1459.9515 | AQ91: =(AQ79+AQ82)/AQ88/3*1000000 -> 1584.1902 | AR91: =(AR79+AR82)/AR88/3*1000000 -> 1389.4202 | AS91: =(AS79+AS82)/AS88/12*1000000 -> 1442.663 | AT91: =(AT79+AT82)/AT88/3*1000000 -> 1284.1827 | AU91: =(AU79+AU82)/AU88/3*1000000 -> 1419.7943 | AV91: =(AV79+AV82)/AV88/3*1000000 -> 1551.725 | AW91: =(AW79+AW82)/AW88/3*1000000 -> 1355.5854 | AX91: =(AX79+AX82)/AX88/12*1000000 -> 1404.794 | AY91: =(AY79+AY82)/AY88/3*1000000 -> 1313.2891 | AZ91: =(AZ79+AZ82)/AZ88/3*1000000 -> 1451.1749 | BA91: =(BA79+BA82)/BA88/3*1000000 -> 1585.7255 | BB91: =(BB79+BB82)/BB88/3*1000000 -> 1386.5186 | BC91: =(BC79+BC82)/BC88/12*1000000 -> 1436.4385 | BD91: =(BD79+BD82)/BD88/3*1000000 -> 1313.2891 | BE91: =(BE79+BE82)/BE88/3*1000000 -> 1451.1749 | BF91: =(BF79+BF82)/BF88/3*1000000 -> 1585.7255 | BG91: =(BG79+BG82)/BG88/3*1000000 -> 1386.5186 | BH91: =(BH79+BH82)/BH88/12*1000000 -> 1436.4385 | BI91: =(BI79+BI82)/BI88/12*1000000 -> 1440.1169 | BJ91: =(BJ79+BJ82)/BJ88/12*1000000 -> 1436.1822 | BK91: =(BK79+BK82)/BK88/12*1000000 -> 1436.1822 | BL91: =(BL79+BL82)/BL88/12*1000000 -> 1436.1822
C92: Depreciation Per Unit Per Month (in whole dollars) | E92: =(E114+E83)/E87*1000000/12 -> 327.35025 | F92: =(F114+F83)/F87*1000000/12 -> 327.35025 | G92: =(G114+G83)/G87*1000000/12 -> 327.35025 | H92: =(H114+H83)/H87*1000000/12 -> 327.35025 | I92: =(I114+I83)/I87*1000000/12 -> 327.35025 | J92: =(J114+J83)/J87*1000000/12 -> 327.35025 | K92: =(K114+K83)/K87*1000000/12 -> 327.35025 | L92: =(L114+L83)/L87*1000000/12 -> 327.35025 | ... T92: =(T114+T83)/T87*1000000/12 -> 258.00228 | U92: =(U114+U83)/U87*1000000/3 -> 297.60757 | V92: =(V114+V83)/V87*1000000/3 -> 270.50519 | W92: =(W114+W83)/W87*1000000/3 -> 161.15764 | X92: =(X114+X83)/X87*1000000/3 -> 300.71019 | Y92: =(Y114+Y83)/Y87*1000000/12 -> 259.83179 | Z92: =(Z114+Z83)/Z87*1000000/3 -> 232.86295 | AA92: =(AA114+AA83)/AA87*1000000/3 -> 77.115977 | AB92: =(AB114+AB83)/AB87*1000000/3 -> 20.652196 | AC92: =(AC114+AC83)/AC87*1000000/3 -> 26.008343 | AD92: =(AD114+AD83)/AD87*1000000/12 -> 80.838584 | AE92: =(AE114+AE83)/AE87*1000000/3 -> -77.963885 | AF92: =(AF114+AF83)/AF87*1000000/3 -> 48.960034 | AG92: =(AG114+AG83)/AG87*1000000/3 -> 198.15349 | AH92: =(AH114+AH83)/AH87*1000000/3 -> 278.29314 | AI92: =(AI114+AI83)/AI87*1000000/12 -> 112.51748 | AJ92: =(AJ114+AJ83)/AJ87*1000000/3 -> 282.4975 | AK92: =(AK114+AK83)/AK87*1000000/3 -> 198.21967 | AL92: =(AL114+AL83)/AL87*1000000/3 -> 295.63711 | AM92: =(AM114+AM83)/AM87*1000000/3 -> 552.35464 | AN92: =(AN114+AN83)/AN87*1000000/12 -> 331.86227 | AO92: =(AO114+AO83)/AO87*1000000/3 -> 648.04643 | AP92: =(AP114+AP83)/AP87*1000000/3 -> 644.06318 | AQ92: =(AQ114+AQ83)/AQ87*1000000/3 -> 590.47714 | AR92: =(AR114+AR83)/AR87*1000000/3 -> 458.14093 | AS92: =(AS114+AS83)/AS87*1000000/12 -> 587.01744 | AT92: =(AT114+AT83)/AT87*1000000/3 -> 372.53768 | AU92: =(AU114+AU83)/AU87*1000000/3 -> 247.85593 | AV92: =(AV114+AV83)/AV87*1000000/3 -> 278.42875 | AW92: =(AW114+AW83)/AW87*1000000/3 -> 346.76736 | AX92: =(AX114+AX83)/AX87*1000000/12 -> 310.36917 | AY92: =AT92*(1+AY108) -> 298.03015 | AZ92: =AU92*(1+AZ108) -> 247.85593 | BA92: =AV92*(1+BA108) -> 278.42875 | BB92: =AW92*(1+BB108) -> 294.75225 | BC92: =(BC114+BC83)/BC87*1000000/12 -> 279.38699 | BD92: =AY92*(1+BD108) -> 298.03015 | BE92: =AZ92*(1+BE108) -> 247.85593 | BF92: =BA92*(1+BF108) -> 278.42875 | BG92: =BB92*(1+BG108) -> 294.75225 | BH92: =(BH114+BH83)/BH87*1000000/12 -> 279.38699 | BI92: =BH92*(1+BI108) -> 279.38699 | BJ92: =BI92*(1+BJ108) -> 279.38699 | BK92: =BJ92*(1+BK108) -> 279.38699 | BL92: =BK92*(1+BL108) -> 279.38699
C93: Percentage of program vehicles as of period end | E93: 0.07 | F93: 0.07 | G93: 0.07 | H93: 0.07 | I93: 0.07 | J93: 0.07 | K93: 0.07 | L93: 0.07 | M93: 0.07 | N93: 0.07 | O93: 0.07 | P93: 0.07 | Q93: 0.07 | R93: 0.07 | S93: 0.09 | T93: 0.11 | U93: 0.09 | V93: 0.06 | W93: 0.04 | X93: 0.02 | Y93: =X93 -> 0.02 | Z93: 0.01 | AA93: 0.05 | AB93: 0.05 | AC93: 0 | AD93: =AC93 -> 0 | AE93: 0 | AF93: 0.01 | AG93: 0 | AH93: 0.01 | AI93: =AH93 -> 0.01 | AJ93: 0.01 | AK93: 0.01 | AL93: 0.01 | AM93: 0.01 | AN93: =AM93 -> 0.01 | AO93: 0.02 | AP93: 0.04 | AQ93: 0.04 | AR93: 0.07 | AS93: =AR93 -> 0.07 | AT93: 0.08 | AU93: 0.07 | AV93: 0.12 | AW93: 0.11 | AX93: =AW93 -> 0.11
C94: Depreciation Per Unit Per Day | E94: =E114/E88/E84*1000000 -> 10.7622 | F94: =F114/F88/F84*1000000 -> 10.7622 | G94: =G114/G88/G84*1000000 -> 10.7622 | H94: =H114/H88/H84*1000000 -> 10.7622 | I94: =I114/I88/I84*1000000 -> 10.7622 | J94: =J114/J88/J84*1000000 -> 10.7622 | K94: =K114/K88/K84*1000000 -> 10.7622 | L94: =L114/L88/L84*1000000 -> 10.7622 | ... BL94: =BL114/BL88/BL84*1000000 -> 9.6892252
C95: DOE per Average Unit Per Day | E95: =E117/E88*1000000/E84 -> 20.636971 | F95: =F117/F88*1000000/F84 -> 20.636971 | G95: =G117/G88*1000000/G84 -> 20.636971 | H95: =H117/H88*1000000/H84 -> 20.636971 | I95: =I117/I88*1000000/I84 -> 20.636971 | J95: =J117/J88*1000000/J84 -> 20.636971 | K95: =K117/K88*1000000/K84 -> 20.636971 | L95: =L117/L88*1000000/L84 -> 20.636971 | ... AX95: =AX117/AX88*1000000/AX84 -> 30.527682 | AY95: =AT95*(1+AY110) -> 29.093778 | AZ95: =AU95*(1+AZ110) -> 29.011878 | BA95: =AV95*(1+BA110) -> 29.144646 | BB95: =AW95*(1+BB110) -> 28.739342 | BC95: =BC117/BC88*1000000/BC84 -> 29.002199 | BD95: =AY95*(1+BD110) -> 28.220964 | BE95: =AZ95*(1+BE110) -> 28.141522 | BF95: =BA95*(1+BF110) -> 28.270307 | BG95: =BB95*(1+BG110) -> 27.877161 | BH95: =BH117/BH88*1000000/BH84 -> 28.132133 | BI95: =BH95*(1+BI110) -> 27.288169 | BJ95: =BI95*(1+BJ110) -> 26.469524 | BK95: =BJ95*(1+BK110) -> 25.675438 | BL95: =BK95*(1+BL110) -> 24.905175
C96: SG&A Per Average Unit Per Day | E96: =E123/E88*1000000/E84 -> 2.2157471 | F96: =F123/F88*1000000/F84 -> 2.2157471 | G96: =G123/G88*1000000/G84 -> 2.2157471 | H96: =H123/H88*1000000/H84 -> 2.2157471 | I96: =I123/I88*1000000/I84 -> 2.2157471 | J96: =J123/J88*1000000/J84 -> 2.2157471 | K96: =K123/K88*1000000/K84 -> 2.2157471 | L96: =L123/L88*1000000/L84 -> 2.2157471 | ... AX96: =AX123/AX88*1000000/AX84 -> 3.4489917 | AY96: =AT96*(1+AY111) -> 3.176844 | AZ96: =AU96*(1+AZ111) -> 3.4542318 | BA96: =AV96*(1+BA111) -> 3.2721157 | BB96: =AW96*(1+BB111) -> 3.4694168 | BC96: =BC123/BC88*1000000/BC84 -> 3.3457781 | BD96: =AY96*(1+BD111) -> 3.176844 | BE96: =AZ96*(1+BE111) -> 3.4542318 | BF96: =BA96*(1+BF111) -> 3.2721157 | BG96: =BB96*(1+BG111) -> 3.4694168 | BH96: =BH123/BH88*1000000/BH84 -> 3.3457781 | BI96: =BH96*(1+BI111) -> 3.3457781 | BJ96: =BI96*(1+BJ111) -> 3.3457781 | BK96: =BJ96*(1+BK111) -> 3.3457781 | BL96: =BK96*(1+BL111) -> 3.3457781
C97: Vehicle Interest Per Average Unit Per Day | E97: =E126/E88*1000000/E84 -> 1.277446 | F97: =F126/F88*1000000/F84 -> 1.277446 | G97: =G126/G88*1000000/G84 -> 1.277446 | H97: =H126/H88*1000000/H84 -> 1.277446 | I97: =I126/I88*1000000/I84 -> 1.277446 | J97: =J126/J88*1000000/J84 -> 1.277446 | K97: =K126/K88*1000000/K84 -> 1.277446 | L97: =L126/L88*1000000/L84 -> 1.277446 | ... AX97: =AX126/AX88*1000000/AX84 -> 3.4900511 | AY97: =AT97*(1+AY112) -> 3.3612837 | AZ97: =AU97*(1+AZ112) -> 3.4801305 | BA97: =AV97*(1+BA112) -> 3.5592459 | BB97: =AW97*(1+BB112) -> 3.5494152 | BC97: =BC126/BC88*1000000/BC84 -> 3.4905158 | BD97: =AY97*(1+BD112) -> 3.8654763 | BE97: =AZ97*(1+BE112) -> 4.00215 | BF97: =BA97*(1+BF112) -> 4.0931328 | BG97: =BB97*(1+BG112) -> 4.0818275 | BH97: =BH126/BH88*1000000/BH84 -> 4.0140931 | BI97: =BH97*(1+BI112) -> 4.0140931 | BJ97: =BI97*(1+BJ112) -> 4.0140931 | BK97: =BJ97*(1+BK112) -> 4.0140931 | BL97: =BK97*(1+BL112) -> 4.0140931
C98: DOE per Average Unit Per Day | E98: =E117/E86*1000 -> 26.007608 | F98: =F117/F86*1000 -> 26.007608 | G98: =G117/G86*1000 -> 26.007608 | H98: =H117/H86*1000 -> 26.007608 | I98: =I117/I86*1000 -> 26.007608 | J98: =J117/J86*1000 -> 26.007608 | K98: =K117/K86*1000 -> 26.007608 | L98: =L117/L86*1000 -> 26.007608 | ... BL98: =BL117/BL86*1000 -> 30.09786
C100: Growth
C101: Available Car Day | F101: =F85/E85-1 -> 0 | G101: =G85/F85-1 -> 0 | H101: =H85/G85-1 -> 0 | I101: =I85/H85-1 -> 0 | J101: =J85/I85-1 -> 0 | K101: =K85/J85-1 -> 0 | L101: =L85/K85-1 -> 0 | M101: =M85/L85-1 -> 0 | ... T101: =T85/S85-1 -> 0.055196291 | Y101: =Y85/T85-1 -> -0.20602806 | Z101: =Z85/U85-1 -> -0.4346972 | AA101: =AA85/V85-1 -> -0.31548264 | AB101: =AB85/W85-1 -> -0.010936583 | AC101: =AC85/X85-1 -> 0.23559693 | AD101: =AD85/Y85-1 -> -0.18620453 | AE101: =AE85/Z85-1 -> 0.25889977 | AF101: =AF85/AA85-1 -> 0.16108674 | ... AX101: =AX85/AS85-1 -> -0.063417696 | BC101: =BC85/AX85-1 -> 0.015082055 | BH101: =BH85/BC85-1 -> 0.02
C102: Transaction Days (in thousands) | F102: =F86/E86-1 -> 0 | G102: =G86/F86-1 -> 0 | H102: =H86/G86-1 -> 0 | I102: =I86/H86-1 -> 0 | J102: =J86/I86-1 -> 0 | K102: =K86/J86-1 -> 0 | L102: =L86/K86-1 -> 0 | M102: =M86/L86-1 -> 0 | ... T102: =T86/S86-1 -> 0.0427932 | Y102: =Y86/T86-1 -> -0.46953978 | Z102: =Z86/U86-1 -> -0.35841465 | AA102: =AA86/V86-1 -> 0.92780006 | AB102: =AB86/W86-1 -> 0.53731011 | AC102: =AC86/X86-1 -> 0.34874616 | AD102: =AD86/Y86-1 -> 0.21055433 | AE102: =AE86/Z86-1 -> 0.26309812 | AF102: =AF86/AA86-1 -> 0.16677337 | ... BH102: =BH86/BC86-1 -> 0.02 | BI102: =BI86/BH86-1 -> 0.022612009 | BJ102: =BJ86/BI86-1 -> 0.017213115 | BK102: =BK86/BJ86-1 -> 0.02 | BL102: =BL86/BK86-1 -> 0.02
C103: Average Vehicles (in whole units) | F103: =F87/E87-1 -> 0 | G103: =G87/F87-1 -> 0 | H103: =H87/G87-1 -> 0 | I103: =I87/H87-1 -> 0 | J103: =J87/I87-1 -> 0 | K103: =K87/J87-1 -> 0 | L103: =L87/K87-1 -> 0 | M103: =M87/L87-1 -> 0 | ... T103: =T87/S87-1 -> 0.055196291 | Y103: =Y87/T87-1 -> -0.20731184 | Z103: =Z87/U87-1 -> -0.42032859 | AA103: =AA87/V87-1 -> -0.30360428 | AB103: =AB87/W87-1 -> 0.029021658 | AC103: =AC87/X87-1 -> 0.28944977 | AD103: =AD87/Y87-1 -> -0.16119457 | AE103: =AE87/Z87-1 -> 0.32272809 | AF103: =AF87/AA87-1 -> 0.2056169 | ... AX103: =AX87/AS87-1 -> -0.069118548 | BC103: =BC87/AX87-1 -> 0.014973807 | BH103: =BH87/BC87-1 -> 0.02
C104: Average Rentable Vehicles (in whole units) | F104: =F88/E88-1 -> 0 | G104: =G88/F88-1 -> 0 | H104: =H88/G88-1 -> 0 | I104: =I88/H88-1 -> 0 | J104: =J88/I88-1 -> 0 | K104: =K88/J88-1 -> 0 | L104: =L88/K88-1 -> 0 | M104: =M88/L88-1 -> 0 | ... T104: =T88/S88-1 -> 0.055196291 | Y104: =Y88/T88-1 -> -0.20731184 | Z104: =Z88/U88-1 -> -0.42841606 | AA104: =AA88/V88-1 -> -0.31548264 | AB104: =AB88/W88-1 -> -0.010936583 | AC104: =AC88/X88-1 -> 0.23559693 | AD104: =AD88/Y88-1 -> -0.18552639 | AE104: =AE88/Z88-1 -> 0.25889977 | AF104: =AF88/AA88-1 -> 0.16108674 | ... AX104: =AX88/AS88-1 -> -0.061103678 | AY104: 0.01 | AZ104: 0.01 | BA104: 0.02 | BB104: 0.02 | BC104: =BC88/AX88-1 -> 0.015041323 | BD104: 0.02 | BE104: 0.02 | BF104: 0.02 | BG104: 0.02 | BH104: =BH88/BC88-1 -> 0.02 | BI104: 0.02 | BJ104: 0.02 | BK104: 0.02 | BL104: 0.02
C105: Vehicle Utilization | F105: =F89/E89-1 -> 0 | G105: =G89/F89-1 -> 0 | H105: =H89/G89-1 -> 0 | I105: =I89/H89-1 -> 0 | J105: =J89/I89-1 -> 0 | K105: =K89/J89-1 -> 0 | L105: =L89/K89-1 -> 0 | M105: =M89/L89-1 -> 0 | ... T105: =T89/S89-1 -> -0.011754298 | Y105: =Y89/T89-1 -> -0.33189047 | Z105: =Z89/U89-1 -> 0.13494105 | AA105: =AA89/V89-1 -> 1.816291 | AB105: =AB89/W89-1 -> 0.55430894 | AC105: =AC89/X89-1 -> 0.091574545 | AD105: =AD89/Y89-1 -> 0.48754124 | AE105: =AE89/Z89-1 -> 0.0033349311 | AF105: =AF89/AA89-1 -> 0.0048976807 | ... AX105: =AX89/AS89-1 -> 0.022407645 | BC105: =BC89/AX89-1 -> 0.012238088 | BH105: =BH89/BC89-1 -> 0
C106: Total RPD (in dollars) | F106: =F90/E90-1 -> 0 | G106: =G90/F90-1 -> 0 | H106: =H90/G90-1 -> 0 | I106: =I90/H90-1 -> 0 | J106: =J90/I90-1 -> 0 | K106: =K90/J90-1 -> 0 | L106: =L90/K90-1 -> 0 | M106: =M90/L90-1 -> 0 | ... T106: =T90/S90-1 -> 0.02674146 | Y106: =Y90/T90-1 -> -0.0066116386 | Z106: =Z90/U90-1 -> 0.091385945 | AA106: =AA90/V90-1 -> 0.59802642 | AB106: =AB90/W90-1 -> 0.43768108 | AC106: =AC90/X90-1 -> 0.4312295 | AD106: =AD90/Y90-1 -> 0.40404419 | AE106: =AE90/Z90-1 -> 0.27393136 | AF106: =AF90/AA90-1 -> 0.027746617 | ... AX106: =AX90/AS90-1 -> -0.045237505 | AY106: 0.01 | AZ106: 0.01 | BA106: 0.01 | BB106: 0.01 | BC106: =BC90/AX90-1 -> 0.010123041 | BD106: 0 | BE106: 0 | BF106: 0 | BG106: 0 | BH106: =BH90/BC90-1 -> 0 | BI106: 0 | BJ106: 0 | BK106: 0 | BL106: 0
C107: Total RPU Per Month (in whole dollars) | F107: =F91/E91-1 -> 0 | G107: =G91/F91-1 -> 0 | H107: =H91/G91-1 -> 0 | I107: =I91/H91-1 -> 0 | J107: =J91/I91-1 -> 0 | K107: =K91/J91-1 -> 0 | L107: =L91/K91-1 -> 0 | M107: =M91/L91-1 -> 0 | ... T107: =T91/S91-1 -> 0.014672835 | Y107: =Y91/T91-1 -> -0.3352329 | Z107: =Z91/U91-1 -> 0.22504707 | AA107: =AA91/V91-1 -> 3.5005074 | AB107: =AB91/W91-1 -> 1.2346006 | AC107: =AC91/X91-1 -> 0.5622937 | AD107: =AD91/Y91-1 -> 1.0868347 | AE107: =AE91/Z91-1 -> 0.27817984 | AF107: =AF91/AA91-1 -> 0.032780192 | ... AX107: =AX91/AS91-1 -> -0.026249375 | BC107: =BC91/AX91-1 -> 0.022526047 | BH107: =BH91/BC91-1 -> 0
C108: Depreciation Per Unit Per Month (in whole dollars) | F108: =F92/E92-1 -> 0 | G108: =G92/F92-1 -> 0 | H108: =H92/G92-1 -> 0 | I108: =I92/H92-1 -> 0 | J108: =J92/I92-1 -> 0 | K108: =K92/J92-1 -> 0 | L108: =L92/K92-1 -> 0 | M108: =M92/L92-1 -> 0 | ... T108: =T92/S92-1 -> -0.064734058 | Y108: =Y92/T92-1 -> 0.0070910853 | Z108: =Z92/U92-1 -> -0.21755031 | AA108: =AA92/V92-1 -> -0.71491868 | AB108: =AB92/W92-1 -> -0.87185097 | AC108: =AC92/X92-1 -> -0.91351027 | AD108: =AD92/Y92-1 -> -0.68888109 | AE108: =AE92/Z92-1 -> -1.3348059 | AF108: =AF92/AA92-1 -> -0.36511167 | ... AX108: =AX92/AS92-1 -> -0.47127776 | AY108: -0.2 | AZ108: 0 | BA108: 0 | BB108: -0.15 | BC108: =BC92/AX92-1 -> -0.099823632 | BD108: 0 | BE108: 0 | BF108: 0 | BG108: 0 | BH108: =BH92/BC92-1 -> 0 | BI108: 0 | BJ108: 0 | BK108: 0 | BL108: 0
C109: Depreciation Per Unit Per Day | F109: =F94/E94-1 -> 0 | G109: =G94/F94-1 -> 0 | H109: =H94/G94-1 -> 0 | I109: =I94/H94-1 -> 0 | J109: =J94/I94-1 -> 0 | K109: =K94/J94-1 -> 0 | L109: =L94/K94-1 -> 0 | M109: =M94/L94-1 -> 0 | ... T109: =T94/S94-1 -> -0.064734058 | Y109: =Y94/T94-1 -> 0.0043394703 | Z109: =Z94/U94-1 -> -0.19766236 | AA109: =AA94/V94-1 -> -0.71355229 | AB109: =AB94/W94-1 -> -0.86667373 | AC109: =AC94/X94-1 -> -0.90974066 | AD109: =AD94/Y94-1 -> -0.67964007 | AE109: =AE94/Z94-1 -> -1.3517811 | AF109: =AF94/AA94-1 -> -0.34328765 | ... AX109: =AX94/AS94-1 -> -0.47434978 | BC109: =BC94/AX94-1 -> -0.10045537 | BH109: =BH94/BC94-1 -> 0
C110: DOE per Average Unit Per Day | F110: =F95/E95-1 -> 0 | G110: =G95/F95-1 -> 0 | H110: =H95/G95-1 -> 0 | I110: =I95/H95-1 -> 0 | J110: =J95/I95-1 -> 0 | K110: =K95/J95-1 -> 0 | L110: =L95/K95-1 -> 0 | M110: =M95/L95-1 -> 0 | ... T110: =T95/S95-1 -> -0.021144301 | Y110: =Y95/T95-1 -> -0.13275394 | Z110: =Z95/U95-1 -> 0.1701812 | AA110: =AA95/V95-1 -> 1.0650276 | AB110: =AB95/W95-1 -> 0.49786298 | AC110: =AC95/X95-1 -> 0.080687466 | AD110: =AD95/Y95-1 -> 0.42241409 | AE110: =AE95/Z95-1 -> 0.11902185 | AF110: =AF95/AA95-1 -> 0.088252994 | ... AX110: =AX95/AS95-1 -> 0.0081127077 | AY110: -0.05 | AZ110: -0.05 | BA110: -0.05 | BB110: -0.05 | BC110: =BC95/AX95-1 -> -0.049970489 | BD110: -0.03 | BE110: -0.03 | BF110: -0.03 | BG110: -0.03 | BH110: =BH95/BC95-1 -> -0.03 | BI110: -0.03 | BJ110: -0.03 | BK110: -0.03 | BL110: -0.03
C111: SG&A Per Average Unit Per Day | F111: na | G111: na | H111: na | I111: na | J111: na | K111: na | L111: na | M111: na | N111: na | O111: na | P111: na | Q111: na | R111: na | S111: =S96/R96-1 -> 0.13671235 | T111: =T96/S96-1 -> -0.0035009081 | Y111: =Y96/T96-1 -> -0.29650034 | Z111: =Z96/U96-1 -> -0.20012087 | AA111: =AA96/V96-1 -> 0.60001508 | AB111: =AB96/W96-1 -> 0.5825248 | AC111: =AC96/X96-1 -> 0.45678575 | AD111: =AD96/Y96-1 -> 0.27158991 | AE111: =AE96/Z96-1 -> 0.31372345 | AF111: =AF96/AA96-1 -> 0.23572388 | ... AX111: =AX96/AS96-1 -> 0.11674517 | AY111: -0.03 | AZ111: -0.03 | BA111: -0.03 | BB111: -0.03 | BC111: =BC96/AX96-1 -> -0.029925724 | BD111: 0 | BE111: 0 | BF111: 0 | BG111: 0 | BH111: =BH96/BC96-1 -> 0 | BI111: 0 | BJ111: 0 | BK111: 0 | BL111: 0
C112: Vehicle Interest Per Average Unit Per Day | F112: na | G112: na | H112: na | I112: na | J112: na | K112: na | L112: na | M112: na | N112: na | O112: na | P112: na | Q112: na | R112: na | S112: =S97/R97-1 -> 0.23121891 | T112: =T97/S97-1 -> 0.12355115 | Y112: =Y97/T97-1 -> 0.18150435 | Z112: =Z97/U97-1 -> 0.48099267 | AA112: =AA97/V97-1 -> 0.14783691 | AB112: =AB97/W97-1 -> -0.55355902 | AC112: =AC97/X97-1 -> -0.60176051 | AD112: =AD97/Y97-1 -> -0.18683259 | AE112: =AE97/Z97-1 -> -0.97793488 | AF112: =AF97/AA97-1 -> -0.60851723 | ... AX112: =AX97/AS97-1 -> 0.13711725 | AY112: 0 | AZ112: 0 | BA112: 0 | BB112: 0 | BC112: =BC97/AX97-1 -> 0.00013314523 | BD112: 0.15 | BE112: 0.15 | BF112: 0.15 | BG112: 0.15 | BH112: =BH97/BC97-1 -> 0.15 | BI112: 0 | BJ112: 0 | BK112: 0 | BL112: 0
C114: Depreciation of revenue earning vehicles and lease charges, net | E114: 1904 | F114: 1904 | G114: 1904 | H114: 1904 | I114: 1904 | J114: 1904 | K114: 1904 | L114: 1904 | M114: 1904 | N114: 1904 | O114: 1904 | P114: 1904 | Q114: 1904 | R114: 1904 | S114: 1678 | T114: 1656 | U114: 463 | V114: 408 | W114: 182 | X114: 269 | Y114: =SUM(U114:X114) -> 1322 | Z114: 210 | AA114: 80 | AB114: 24 | AC114: 30 | AD114: =SUM(Z114:AC114) -> 344 | AE114: -93 | AF114: 61 | AG114: 252 | AH114: 333 | AI114: =SUM(AE114:AH114) -> 553 | AJ114: 349 | AK114: 272 | AL114: 414 | AM114: 740 | AN114: =SUM(AJ114:AM114) -> 1775 | AO114: 876 | AP114: 905 | AQ114: 822 | AR114: 595 | AS114: =SUM(AO114:AR114) -> 3198 | AT114: 462 | AU114: 325 | AV114: 355 | AW114: 432 | AX114: =SUM(AT114:AW114) -> 1574 | AY114: =AY92*AY87*3/1000000 -> 373.296 | AZ114: =AZ92*AZ87*3/1000000 -> 327.24 | BA114: =BA92*BA87*3/1000000 -> 362.1 | BB114: =BB92*BB87*3/1000000 -> 374.544 | BC114: =SUM(AY114:BB114) -> 1437.18 | BD114: =BD92*BD87*3/1000000 -> 380.76192 | BE114: =BE92*BE87*3/1000000 -> 333.7848 | BF114: =BF92*BF87*3/1000000 -> 369.342 | BG114: =BG92*BG87*3/1000000 -> 382.03488 | BH114: =SUM(BD114:BG114) -> 1465.9236 | BI114: =BI92*BI87*12/1000000 -> 1495.2421 | BJ114: =BJ92*BJ87*12/1000000 -> 1525.1469 | BK114: =BK92*BK87*12/1000000 -> 1555.6499 | BL114: =BL92*BL87*12/1000000 -> 1586.7628
C115: % of Rev | E115: =E114/E79 -> 0.31765098 | F115: =F114/F79 -> 0.31765098 | G115: =G114/G79 -> 0.31765098 | H115: =H114/H79 -> 0.31765098 | I115: =I114/I79 -> 0.31765098 | J115: =J114/J79 -> 0.31765098 | K115: =K114/K79 -> 0.31765098 | L115: =L114/L79 -> 0.31765098 | ... BL115: =BL114/BL79 -> 0.20520651
C117: Direct vehicle and operating expenses | E117: 3651 | F117: 3651 | G117: 3651 | H117: 3651 | I117: 3651 | J117: 3651 | K117: 3651 | L117: 3651 | M117: 3651 | N117: 3651 | O117: 3651 | P117: 3651 | Q117: 3651 | R117: 3651 | S117: 4014 | T117: 4146 | U117: 969 | V117: 561 | W117: 648 | X117: 680 | Y117: =SUM(U117:X117) -> 2858 | Z117: 641 | AA117: 793 | AB117: 960 | AC117: 908 | AD117: =SUM(Z117:AC117) -> 3302 | AE117: 903 | AF117: 1002 | AG117: 1077 | AH117: 1098 | AI117: =SUM(AE117:AH117) -> 4080 | AJ117: 1039 | AK117: 1139 | AL117: 1241 | AM117: 1163 | AN117: =SUM(AJ117:AM117) -> 4582 | AO117: 1152 | AP117: 1199 | AQ117: 1202 | AR117: 1173 | AS117: =SUM(AO117:AR117) -> 4726 | AT117: 1066 | AU117: 1132 | AV117: 1155 | AW117: 1108 | AX117: =SUM(AT117:AW117) -> 4461 | AY117: =AY95*AY88*AY84/1000000 -> 1022.827 | AZ117: =AZ95*AZ88*AZ84/1000000 -> 1086.154 | BA117: =BA95*BA88*BA84/1000000 -> 1119.195 | BB117: =BB95*BB88*BB84/1000000 -> 1073.652 | BC117: =SUM(AY117:BB117) -> 4301.828 | BD117: =BD95*BD88*BD84/1000000 -> 1011.985 | BE117: =BE95*BE88*BE84/1000000 -> 1074.6408 | BF117: =BF95*BF88*BF84/1000000 -> 1107.3315 | BG117: =BG95*BG88*BG84/1000000 -> 1062.2713 | BH117: =SUM(BD117:BG117) -> 4256.2286 | BI117: =BI95*BI88*BI84/1000000 -> 4222.6499 | BJ117: =BJ95*BJ88*BJ84/1000000 -> 4166.4748 | BK117: =BK95*BK88*BK84/1000000 -> 4122.3102 | BL117: =BL95*BL88*BL84/1000000 -> 4078.6137
C118: % of Rev | E118: =E117/E79 -> 0.60910911 | F118: =F117/F79 -> 0.60910911 | G118: =G117/G79 -> 0.60910911 | H118: =H117/H79 -> 0.60910911 | I118: =I117/I79 -> 0.60910911 | J118: =J117/J79 -> 0.60910911 | K118: =K117/K79 -> 0.60910911 | L118: =L117/L79 -> 0.60910911 | ... BL118: =BL117/BL79 -> 0.52746262
C120: Non-vehicle depreciation and amortization | E120: 181 | F120: 181 | G120: 181 | H120: 181 | I120: 181 | J120: 181 | K120: 181 | L120: 181 | M120: 181 | N120: 181 | O120: 181 | P120: 181 | Q120: 181 | R120: 181 | S120: 159 | T120: 150 | U120: 45 | V120: 45 | W120: 45 | X120: 45 | Y120: =SUM(U120:X120) -> 180 | Z120: 44 | AA120: 43 | AB120: 42 | AC120: 36 | AD120: =SUM(Z120:AC120) -> 165 | AE120: 26 | AF120: 30 | AG120: 29 | AH120: 29 | AI120: =SUM(AE120:AH120) -> 114 | AJ120: 28 | AK120: 27 | AL120: 27 | AM120: 43 | AN120: =SUM(AJ120:AM120) -> 125 | AO120: 25 | AP120: 28 | AQ120: 28 | AR120: 28 | AS120: =SUM(AO120:AR120) -> 109 | AT120: 26 | AU120: 23 | AV120: 23 | AW120: 24 | AX120: =SUM(AT120:AW120) -> 96 | AY120: =AT120 -> 26 | AZ120: =AU120 -> 23 | BA120: =AV120 -> 23 | BB120: =AW120 -> 24 | BC120: =SUM(AY120:BB120) -> 96 | BD120: =AY120 -> 26 | BE120: =AZ120 -> 23 | BF120: =BA120 -> 23 | BG120: =BB120 -> 24 | BH120: =SUM(BD120:BG120) -> 96 | BI120: =BH120 -> 96 | BJ120: =BI120 -> 96 | BK120: =BJ120 -> 96 | BL120: =BK120 -> 96
...
